Workbook
Name NativeTimeline_Order_Date: #N/A
Name Slicer_Loyalty_Card: #N/A
Name Slicer_Roast_type_Name: #N/A
Name Slicer_Size: #N/A

Sheet Detail1
A1: Details for Sum of Sales - Months (Order Date): Apr, Years (Order Date): 2019, Coffee Type name :
A3: Order ID | B3: Order Date | C3: Customer ID | D3: Product ID | E3: Quantity | F3: Customer Name | G3: Email | H3: Country | I3: Coffee Type | J3: Roast Type | K3: Size | L3: Unit Price | M3: Sales | N3: Coffee Type name | O3: Roast type Name
A4: NCH-55389-562 | B4: 43582 | C4: 86579-92122-OC | D4: A-L-0.2 | E4: 2 | F4: Brenn Dundredge | H4: #N/A | I4: Coffee Type | J4: Roast Type | K4: Size | L4: Unit Price | M4: #VALUE!

Sheet Detail2
A1: Details for Sum of Sales - Years (Order Date): 2019
A3: Order ID | B3: Order Date | C3: Customer ID | D3: Product ID | E3: Quantity | F3: Customer Name | G3: Email | H3: Country | I3: Coffee Type | J3: Roast Type | K3: Size | L3: Unit Price | M3: Sales | N3: Coffee Type name | O3: Roast type Name
A4: GTT-73214-334 | B4: 43485 | C4: 98636-90072-YE | D4: A-L-1 | E4: 6 | F4: Nobe Buney | G4: nbuneylx@jugem.jp | H4: United States | I4: Ara | J4: L | K4: 0.5 | L4: 7.77 | M4: 46.62 | N4: Arabica | O4: Light
A5: FWU-44971-444 | B5: 43476 | C5: 12190-25421-WM | D5: A-D-2.5 | E5: 3 | F5: Marvin Malloy | G5: mmalloyi6@seattletimes.com | H5: United States | I5: Ara | J5: D | K5: 1 | L5: 9.95 | M5: 29.85 | N5: Arabica | O5: Dark
A6: ABO-29054-365 | B6: 43484 | C6: 00256-19905-YG | D6: A-M-0.5 | E6: 6 | F6: Stanislaus Valsler | H6: Ireland | I6: Ara | J6: M | K6: 0.2 | L6: 3.375 | M6: 20.25 | N6: Arabica | O6: Medium
A7: GPW-43956-761 | B7: 43491 | C7: 09667-09231-YM | D7: E-L-0.5 | E7: 6 | F7: Bearnard Wardell | G7: bwardellqu@adobe.com | H7: United States | I7: Exc | J7: L | K7: 0.2 | L7: 4.455 | M7: 26.73 | N7: Excelsa | O7: Light
A8: TNR-84447-052 | B8: 43474 | C8: 34419-18068-AG | D8: E-D-2.5 | E8: 4 | F8: Dolores Duffie | G8: dduffiepr@time.com | H8: United States | I8: Exc | J8: D | K8: 1 | L8: 12.15 | M8: 48.6 | N8: Excelsa | O8: Dark
A9: IMP-12563-728 | B9: 43468 | C9: 68346-14810-UA | D9: E-L-0.5 | E9: 6 | F9: Spencer Wastell | H9: United States | I9: Exc | J9: L | K9: 0.2 | L9: 4.455 | M9: 26.73 | N9: Excelsa | O9: Light
A10: KFJ-46568-890 | B10: 43485 | C10: 71003-85639-HB | D10: E-L-0.5 | E10: 2 | F10: Lyell Murch | H10: United States | I10: Exc | J10: L | K10: 0.2 | L10: 4.455 | M10: 8.91 | N10: Excelsa | O10: Light
A11: CYZ-37122-164 | B11: 43471 | C11: 21798-04171-XC | D11: E-M-0.5 | E11: 2 | F11: Wilton Cottier | G11: wcottierj3@cafepress.com | H11: United States | I11: Exc | J11: M | K11: 0.2 | L11: 4.125 | M11: 8.25 | N11: Excelsa | O11: Medium
A12: CTE-31437-326 | B12: 43467 | C12: 22721-63196-UJ | D12: E-M-0.2 | E12: 4 | F12: Gladi Ducker | G12: gduckerdx@patch.com | H12: United Kingdom | I12: Exc | J12: L | K12: 2.5 | L12: 34.155 | M12: 136.62 | N12: Excelsa | O12: Light
A13: EQE-31648-909 | B13: 43483 | C13: 19821-05175-WZ | D13: E-D-0.5 | E13: 5 | F13: Angie Rizzetti | G13: arizzetti55@naver.com | H13: United States | I13: Exc | J13: D | K13: 0.2 | L13: 3.645 | M13: 18.225 | N13: Excelsa | O13: Dark
A14: LDK-71031-121 | B14: 43475 | C14: 84761-40784-SV | D14: L-L-2.5 | E14: 1 | F14: Andie Rudram | G14: arudramka@prnewswire.com | H14: United States | I14: Lib | J14: L | K14: 1 | L14: 15.85 | M14: 15.85 | N14: Liberica | O14: Light
A15: AYY-83051-752 | B15: 43487 | C15: 46431-09298-OU | D15: L-L-1 | E15: 6 | F15: Carolee Winchcombe | G15: cwinchcombeho@jiathis.com | H15: United States | I15: Lib | J15: L | K15: 0.5 | L15: 9.51 | M15: 57.06 | N15: Liberica | O15: Light
A16: CTE-31437-326 | B16: 43467 | C16: 22721-63196-UJ | D16: L-D-1 | E16: 4 | F16: Gladi Ducker | G16: gduckerdx@patch.com | H16: #N/A | I16: Lib | J16: D | K16: 0.5 | L16: 7.77 | M16: 31.08 | N16: Liberica | O16: Dark
A17: VJF-46305-323 | B17: 43483 | C17: 68555-89840-GZ | D17: L-D-0.5 | E17: 2 | F17: Morgen Seson | G17: msesonck@census.gov | H17: United States | I17: Lib | J17: D | K17: 0.2 | L17: 3.885 | M17: 7.77 | N17: Liberica | O17: Dark
A18: EZT-46571-659 | B18: 43467 | C18: 03396-68805-ZC | D18: R-M-0.5 | E18: 3 | F18: Guthrey Petracci | G18: gpetracci8@livejournal.com | H18: United States | I18: Rob | J18: M | K18: 0.2 | L18: 2.985 | M18: 8.955 | N18: Robusta | O18: Medium
A19: TID-21626-411 | B19: 43468 | C19: 19383-33606-PW | D19: R-L-0.5 | E19: 3 | F19: Suzanna Bollam | G19: sbollamlf@list-manage.com | H19: United States | I19: Rob | J19: L | K19: 0.2 | L19: 3.585 | M19: 10.755 | N19: Robusta | O19: Light
A20: OUQ-73954-002 | B20: 43471 | C20: 66308-13503-KD | D20: R-M-0.2 | E20: 4 | F20: Krissie Hammett | G20: khammettgm@dmoz.org | H20: United States | I20: Rob | J20: L | K20: 2.5 | L20: 27.485 | M20: 109.94 | N20: Robusta | O20: Light
A21: KAR-24978-271 | B21: 43475 | C21: 23187-65750-HZ | D21: R-M-1 | E21: 6 | F21: Starr Arpin | G21: sarpinep@moonfruit.com | H21: United States | I21: Rob | J21: M | K21: 0.5 | L21: 5.97 | M21: 35.82 | N21: Robusta | O21: Medium
A22: CTE-31437-326 | B22: 43467 | C22: 22721-63196-UJ | D22: L-L-0.2 | E22: 3 | F22: Gladi Ducker | G22: gduckerdx@patch.com | H22: #N/A | I22: Rob | J22: D | K22: 2.5 | L22: 20.585 | M22: 61.755 | N22: Robusta | O22: Dark
A23: CTE-31437-326 | B23: 43467 | C23: 22721-63196-UJ | D23: R-M-0.2 | E23: 4 | F23: Gladi Ducker | G23: gduckerdx@patch.com | H23: United Kingdom | I23: Rob | J23: L | K23: 2.5 | L23: 27.485 | M23: 109.94 | N23: Robusta | O23: Light
A24: EVP-43500-491 | B24: 43516 | C24: 49231-44455-IC | D24: A-M-0.5 | E24: 4 | F24: Selene Shales | G24: sshalesq@umich.edu | H24: United States | I24: Ara | J24: M | K24: 0.2 | L24: 3.375 | M24: 13.5 | N24: Arabica | O24: Medium
A25: RYZ-14633-602 | B25: 43516 | C25: 14158-30713-OB | D25: A-D-1 | E25: 4 | F25: Mozelle Calcutt | G25: mcalcuttt@baidu.com | H25: Ireland | I25: Ara | J25: D | K25: 0.5 | L25: 5.97 | M25: 23.88 | N25: Arabica | O25: Dark
A26: ONW-00560-570 | B26: 43521 | C26: 32900-82606-BO | D26: A-M-1 | E26: 2 | F26: Claudie Weond | G26: cweondo8@theglobeandmail.com | H26: United States | I26: Ara | J26: M | K26: 0.5 | L26: 6.75 | M26: 13.5 | N26: Arabica | O26: Medium
A27: OLF-77983-457 | B27: 43512 | C27: 51901-35210-UI | D27: A-L-2.5 | E27: 2 | F27: Gabriel Starcks | G27: gstarcksgi@abc.net.au | H27: United States | I27: Ara | J27: L | K27: 1 | L27: 12.95 | M27: 25.9 | N27: Arabica | O27: Light
A28: EAY-89850-211 | B28: 43515 | C28: 43155-71724-XP | D28: A-D-0.2 | E28: 2 | F28: Herbie Peppard | H28: United States | I28: Ara | J28: M | K28: 2.5 | L28: 25.875 | M28: 51.75 | N28: Arabica | O28: Medium
A29: XEE-37895-169 | B29: 43516 | C29: 14888-85625-TM | D29: A-L-2.5 | E29: 3 | F29: Perry Lyfield | G29: plyfielde3@baidu.com | H29: United States | I29: Ara | J29: L | K29: 1 | L29: 12.95 | M29: 38.85 | N29: Arabica | O29: Light
A30: LTD-71429-845 | B30: 43520 | C30: 03157-23165-UB | D30: A-L-0.5 | E30: 1 | F30: Flory Crumpe | G30: fcrumpe7u@ftc.gov | H30: United Kingdom | I30: Ara | J30: L | K30: 0.2 | L30: 3.885 | M30: 3.885 | N30: Arabica | O30: Light
A31: AOL-13866-711 | B31: 43510 | C31: 83490-88357-LJ | D31: E-M-1 | E31: 4 | F31: Eustace Stenton | G31: estentonms@google.it | H31: United States | I31: Exc | J31: M | K31: 0.5 | L31: 8.25 | M31: 33 | N31: Excelsa | O31: Medium
A32: BPG-68988-842 | B32: 43517 | C32: 53631-24432-SY | D32: E-M-0.5 | E32: 5 | F32: Irvine Phillpot | G32: iphillpoten@buzzfeed.com | H32: United Kingdom | I32: Exc | J32: M | K32: 0.2 | L32: 4.125 | M32: 20.625 | N32: Excelsa | O32: Medium
A33: GZS-50547-887 | B33: 43501 | C33: 61600-55136-UM | D33: E-D-1 | E33: 2 | F33: Corinna Catcheside | G33: ccatchesideaa@macromedia.com | H33: United States | I33: Exc | J33: D | K33: 0.5 | L33: 7.29 | M33: 14.58 | N33: Excelsa | O33: Dark
A34: OJU-34452-896 | B34: 43500 | C34: 60799-92593-CX | D34: E-L-0.5 | E34: 1 | F34: Abba Pummell | H34: United States | I34: Exc | J34: L | K34: 0.2 | L34: 4.455 | M34: 4.455 | N34: Excelsa | O34: Light
A35: CZD-56716-840 | B35: 43524 | C35: 15456-29250-RU | D35: L-D-2.5 | E35: 4 | F35: Jaimie Hatz | H35: United States | I35: Lib | J35: D | K35: 1 | L35: 12.95 | M35: 51.8 | N35: Liberica | O35: Dark
A36: TRZ-94735-865 | B36: 43501 | C36: 54462-58311-YF | D36: L-M-0.5 | E36: 4 | F36: Teddi Quadri | G36: tquadrikr@opensource.org | H36: Ireland | I36: Lib | J36: M | K36: 0.2 | L36: 4.365 | M36: 17.46 | N36: Liberica | O36: Medium
A37: CZG-01299-952 | B37: 43508 | C37: 09540-70637-EV | D37: L-D-1 | E37: 2 | F37: Jarret Toye | G37: jtoyekg@pinterest.com | H37: Ireland | I37: Lib | J37: D | K37: 0.5 | L37: 7.77 | M37: 15.54 | N37: Liberica | O37: Dark
A38: QLC-52637-305 | B38: 43506 | C38: 34317-87258-HQ | D38: L-D-2.5 | E38: 4 | F38: Doralin Baison | H38: Ireland | I38: Lib | J38: D | K38: 1 | L38: 12.95 | M38: 51.8 | N38: Liberica | O38: Dark
A39: JUO-34131-517 | B39: 43509 | C39: 07972-83748-JI | D39: L-D-1 | E39: 6 | F39: Rivy Farington | H39: United States | I39: Lib | J39: D | K39: 0.5 | L39: 7.77 | M39: 46.62 | N39: Liberica | O39: Dark
A40: HPD-65272-772 | B40: 43521 | C40: 57504-13456-UO | D40: L-M-2.5 | E40: 1 | F40: Parsifal Metrick | G40: pmetrick7r@rakuten.co.jp | H40: United States | I40: Lib | J40: M | K40: 1 | L40: 14.55 | M40: 14.55 | N40: Liberica | O40: Medium
A41: ZYQ-15797-695 | B41: 43521 | C41: 79436-73011-MM | D41: R-D-0.5 | E41: 5 | F41: Pammi Endacott | H41: United Kingdom | I41: Rob | J41: D | K41: 0.2 | L41: 2.685 | M41: 13.425 | N41: Robusta | O41: Dark
A42: EEJ-16185-108 | B42: 43505 | C42: 65552-60476-KY | D42: L-L-0.2 | E42: 5 | F42: Nona Linklater | H42: United States | I42: Rob | J42: D | K42: 2.5 | L42: 20.585 | M42: 102.925 | N42: Robusta | O42: Dark
A43: EZB-68383-559 | B43: 43517 | C43: 90123-01967-KS | D43: R-L-1 | E43: 6 | F43: Becca Ableson | H43: United States | I43: Rob | J43: L | K43: 0.5 | L43: 7.17 | M43: 43.02 | N43: Robusta | O43: Light
A44: WMU-87639-108 | B44: 43507 | C44: 71891-51101-VQ | D44: R-D-0.5 | E44: 1 | F44: Cecily Stebbings | G44: cstebbingsi2@drupal.org | H44: United States | I44: Rob | J44: D | K44: 0.2 | L44: 2.685 | M44: 2.685 | N44: Robusta | O44: Dark
A45: RWI-84131-848 | B45: 43518 | C45: 16385-11286-NX | D45: R-D-2.5 | E45: 2 | F45: Mohandis Spurden | G45: mspurdencj@exblog.jp | H45: United States | I45: Rob | J45: D | K45: 1 | L45: 8.95 | M45: 17.9 | N45: Robusta | O45: Dark
A46: DJG-14442-608 | B46: 43502 | C46: 75716-12782-SS | D46: R-D-1 | E46: 3 | F46: Gale Croysdale | G46: gcroysdaleb6@nih.gov | H46: United States | I46: Rob | J46: D | K46: 0.5 | L46: 5.37 | M46: 16.11 | N46: Robusta | O46: Dark
A47: VAU-44387-624 | B47: 43544 | C47: 99643-51048-IQ | D47: A-M-0.2 | E47: 6 | F47: Minni Alabaster | G47: malabasterg@hexun.com | H47: United States | I47: Ara | J47: L | K47: 2.5 | L47: 29.785 | M47: 178.71 | N47: Arabica | O47: Light
A48: YKX-23510-272 | B48: 43541 | C48: 56991-05510-PR | D48: A-L-2.5 | E48: 2 | F48: Janella Eden | G48: jedenll@e-recht24.de | H48: United States | I48: Ara | J48: L | K48: 1 | L48: 12.95 | M48: 25.9 | N48: Arabica | O48: Light
A49: SHP-55648-472 | B49: 43554 | C49: 46818-20198-GB | D49: A-M-1 | E49: 6 | F49: Corrie Wass | G49: cwassif@prweb.com | H49: United States | I49: Ara | J49: M | K49: 0.5 | L49: 6.75 | M49: 40.5 | N49: Arabica | O49: Medium
A50: EXP-21628-670 | B50: 43526 | C50: 94447-35885-HK | D50: A-M-2.5 | E50: 3 | F50: Wallis Bernth | G50: wbernthhe@miitbeian.gov.cn | H50: United States | I50: Ara | J50: M | K50: 1 | L50: 11.25 | M50: 33.75 | N50: Arabica | O50: Medium
A51: GQR-12490-152 | B51: 43538 | C51: 22832-98538-RB | D51: R-L-0.2 | E51: 1 | F51: Sidney Gawen | G51: sgaweng7@creativecommons.org | H51: United States | I51: Ara | J51: D | K51: 2.5 | L51: 22.885 | M51: 22.885 | N51: Arabica | O51: Dark
A52: NXM-89323-646 | B52: 43546 | C52: 28158-93383-CK | D52: E-D-1 | E52: 1 | F52: Kameko Philbrick | G52: kphilbrickpu@cdc.gov | H52: United States | I52: Exc | J52: D | K52: 0.5 | L52: 7.29 | M52: 7.29 | N52: Excelsa | O52: Dark
A53: YWM-07310-594 | B53: 43526 | C53: 66028-99867-WJ | D53: E-M-0.5 | E53: 5 | F53: Margie Palleske | G53: mpalleskeo4@nyu.edu | H53: United States | I53: Exc | J53: M | K53: 0.2 | L53: 4.125 | M53: 20.625 | N53: Excelsa | O53: Medium
A54: YWH-50638-556 | B54: 43538 | C54: 89442-35633-HJ | D54: E-L-0.5 | E54: 4 | F54: Else Langcaster | G54: elangcaster2l@spotify.com | H54: United Kingdom | I54: Exc | J54: L | K54: 0.2 | L54: 4.455 | M54: 17.82 | N54: Excelsa | O54: Light
A55: IRJ-67095-738 | B55: 43544 | C55: 86447-02699-UT | D55: E-M-2.5 | E55: 2 | F55: Minny Chamberlayne | G55: mchamberlayne4r@bigcartel.com | H55: United States | I55: Exc | J55: M | K55: 1 | L55: 13.75 | M55: 27.5 | N55: Excelsa | O55: Medium
... A60: VGI-33205-360 | B60: 43545 | C60: 96762-10814-DA | D60: L-M-0.5 | E60: 6 | F60: Jereme Gippes | G60: jgippesm0@cloudflare.com | H60: United Kingdom | I60: Lib | J60: M | K60: 0.2 | L60: 4.365 | M60: 26.19 | N60: Liberica | O60: Medium
A61: KCY-61732-849 | B61: 43540 | C61: 11349-55147-SN | D61: L-D-1 | E61: 2 | F61: Nicolas Aiton | H61: Ireland | I61: Lib | J61: D | K61: 0.5 | L61: 7.77 | M61: 15.54 | N61: Liberica | O61: Dark
A62: XTH-67276-442 | B62: 43527 | C62: 73799-04749-BM | D62: L-M-2.5 | E62: 4 | F62: Bertine Byrd | G62: bbyrdha@4shared.com | H62: United States | I62: Lib | J62: M | K62: 1 | L62: 14.55 | M62: 58.2 | N62: Liberica | O62: Medium
A63: RKW-81145-984 | B63: 43535 | C63: 98661-69719-VI | D63: L-L-1 | E63: 3 | F63: Celia Bakeup | G63: cbakeupe8@globo.com | H63: United States | I63: Lib | J63: L | K63: 0.5 | L63: 9.51 | M63: 28.53 | N63: Liberica | O63: Light
A64: MBM-55936-917 | B64: 43536 | C64: 55989-39849-WO | D64: L-D-0.5 | E64: 3 | F64: Andrej Havick | G64: ahavickat@nsw.gov.au | H64: United States | I64: Lib | J64: D | K64: 0.2 | L64: 3.885 | M64: 11.655 | N64: Liberica | O64: Dark
A65: BDM-03174-485 | B65: 43540 | C65: 29581-13303-VB | D65: R-L-0.5 | E65: 4 | F65: Wright Caldero | G65: wcalderom3@stumbleupon.com | H65: United States | I65: Rob | J65: L | K65: 0.2 | L65: 3.585 | M65: 14.34 | N65: Robusta | O65: Light
A66: YXF-57218-272 | B66: 43539 | C66: 55374-03175-IA | D66: R-M-0.2 | E66: 6 | F66: Samuele Klaaassen | H66: United States | I66: Rob | J66: L | K66: 2.5 | L66: 27.485 | M66: 164.91 | N66: Robusta | O66: Light
A67: CPV-90280-133 | B67: 43544 | C67: 66458-91190-YC | D67: R-D-0.2 | E67: 3 | F67: Marja Urion | G67: murione5@alexa.com | H67: #N/A | I67: Rob | J67: M | K67: 2.5 | L67: 22.885 | M67: 68.655 | N67: Robusta | O67: Medium
A68: VQV-59984-866 | B68: 43532 | C68: 48854-01899-FN | D68: R-D-0.2 | E68: 3 | F68: Vanya Skullet | G68: vskulletah@tinyurl.com | H68: Ireland | I68: Rob | J68: M | K68: 2.5 | L68: 22.885 | M68: 68.655 | N68: Robusta | O68: Medium
A69: OTA-40969-710 | B69: 43538 | C69: 77877-11993-QH | D69: R-L-1 | E69: 5 | F69: Monique Canty | G69: mcanty79@jigsy.com | H69: United States | I69: Rob | J69: L | K69: 0.5 | L69: 7.17 | M69: 35.85 | N69: Robusta | O69: Light
A70: NCH-55389-562 | B70: 43582 | C70: 86579-92122-OC | D70: A-L-0.2 | E70: 2 | F70: Brenn Dundredge | H70: #N/A | I70: Coffee Type | J70: Roast Type | K70: Size | L70: Unit Price | M70: #VALUE!
A71: OQA-93249-841 | B71: 43560 | C71: 03917-13632-KC | D71: A-M-2.5 | E71: 6 | F71: Herta Layne | H71: United States | I71: Ara | J71: M | K71: 1 | L71: 11.25 | M71: 67.5 | N71: Arabica | O71: Medium
A72: IJK-34441-720 | B72: 43560 | C72: 97201-58870-WB | D72: A-M-0.5 | E72: 6 | F72: Darcy Lochran | H72: United States | I72: Ara | J72: M | K72: 0.2 | L72: 3.375 | M72: 20.25 | N72: Arabica | O72: Medium
A73: SUB-13006-125 | B73: 43572 | C73: 26103-41504-IB | D73: A-L-0.5 | E73: 5 | F73: Ami Arnow | G73: aarnow28@arizona.edu | H73: United States | I73: Ara | J73: L | K73: 0.2 | L73: 3.885 | M73: 19.425 | N73: Arabica | O73: Light
A74: AGQ-06534-750 | B74: 43579 | C74: 52798-46508-HP | D74: A-L-1 | E74: 5 | F74: Kevan Grinsted | G74: kgrinstedj4@google.com.br | H74: Ireland | I74: Ara | J74: L | K74: 0.5 | L74: 7.77 | M74: 38.85 | N74: Arabica | O74: Light
A75: JUA-13580-095 | B75: 43556 | C75: 55265-75151-AK | D75: R-L-0.2 | E75: 4 | F75: Manuel Darrigoe | G75: mdarrigoebu@hud.gov | H75: Ireland | I75: Ara | J75: D | K75: 2.5 | L75: 22.885 | M75: 91.54 | N75: Arabica | O75: Dark
A76: FEP-36895-658 | B76: 43563 | C76: 44699-43836-UH | D76: R-L-0.2 | E76: 6 | F76: Yuma Skipsey | G76: yskipsey9z@spotify.com | H76: United Kingdom | I76: Ara | J76: D | K76: 2.5 | L76: 22.885 | M76: 137.31 | N76: Arabica | O76: Dark
A77: NCH-55389-562 | B77: 43582 | C77: 86579-92122-OC | D77: E-L-1 | E77: 1 | F77: Brenn Dundredge | H77: #N/A | I77: Exc | J77: L | K77: 0.5 | L77: 8.91 | M77: 8.91 | N77: Excelsa | O77: Light
A78: NCH-55389-562 | B78: 43582 | C78: 86579-92122-OC | D78: E-L-2.5 | E78: 5 | F78: Brenn Dundredge | H78: #N/A | I78: Exc | J78: L | K78: 1 | L78: 14.85 | M78: 74.25 | N78: Excelsa | O78: Light
A79: KMS-49214-806 | B79: 43585 | C79: 50384-52703-LA | D79: E-L-2.5 | E79: 4 | F79: Lyndsey MacManus | G79: lmacmanusmu@imdb.com | H79: United States | I79: Exc | J79: L | K79: 1 | L79: 14.85 | M79: 59.4 | N79: Excelsa | O79: Light
A80: RRP-51647-420 | B80: 43573 | C80: 89292-52335-YZ | D80: E-D-1 | E80: 3 | F80: Livy Lathleiff | G80: llathleiffc9@nationalgeographic.com | H80: Ireland | I80: Exc | J80: D | K80: 0.5 | L80: 7.29 | M80: 21.87 | N80: Excelsa | O80: Dark
A81: CXD-74176-600 | B81: 43562 | C81: 70624-19112-AO | D81: E-L-0.5 | E81: 4 | F81: Chickie Ragless | G81: craglessc7@webmd.com | H81: Ireland | I81: Exc | J81: L | K81: 0.2 | L81: 4.455 | M81: 17.82 | N81: Excelsa | O81: Light
A82: HDQ-86094-507 | B82: 43582 | C82: 32481-61533-ZJ | D82: E-D-1 | E82: 6 | F82: Parker Tofful | G82: ptoffula4@posterous.com | H82: United States | I82: Exc | J82: D | K82: 0.5 | L82: 7.29 | M82: 43.74 | N82: Excelsa | O82: Dark
A83: CXI-04933-855 | B83: 43582 | C83: 62923-29397-KX | D83: E-L-2.5 | E83: 6 | F83: Lacee Tanti | G83: ltanti8b@techcrunch.com | H83: United States | I83: Exc | J83: L | K83: 1 | L83: 14.85 | M83: 89.1 | N83: Excelsa | O83: Light
A84: LGD-24408-274 | B84: 43580 | C84: 13694-25001-LX | D84: L-L-0.5 | E84: 3 | F84: Silvio Strase | G84: sstrase11@booking.com | H84: United States | I84: Lib | J84: L | K84: 0.2 | L84: 4.755 | M84: 14.265 | N84: Liberica | O84: Light
A85: VVL-95291-039 | B85: 43573 | C85: 96516-97464-MF | D85: E-L-0.2 | E85: 2 | F85: Silvanus Enefer | G85: senefermm@blog.com | H85: United States | I85: Lib | J85: D | K85: 2.5 | L85: 29.785 | M85: 59.57 | N85: Liberica | O85: Dark
A86: ZHQ-30471-635 | B86: 43563 | C86: 40600-58915-WZ | D86: L-M-0.5 | E86: 5 | F86: Sharona Danilchik | G86: sdanilchikl6@mit.edu | H86: United Kingdom | I86: Lib | J86: M | K86: 0.2 | L86: 4.365 | M86: 21.825 | N86: Liberica | O86: Medium
A87: PMV-54491-220 | B87: 43566 | C87: 87242-18006-IR | D87: L-M-0.2 | E87: 2 | F87: Lyon Ibert | G87: libertkl@huffingtonpost.com | H87: United States | I87: Lib | J87: L | K87: 2.5 | L87: 36.455 | M87: 72.91 | N87: Liberica | O87: Light
A88: YGY-98425-969 | B88: 43556 | C88: 63787-96257-TQ | D88: L-M-1 | E88: 1 | F88: Merrel Steptow | G88: msteptow35@earthlink.net | H88: Ireland | I88: Lib | J88: M | K88: 0.5 | L88: 8.73 | M88: 8.73 | N88: Liberica | O88: Medium
A89: MWP-46239-785 | B89: 43582 | C89: 87979-56781-YV | D89: L-M-0.2 | E89: 5 | F89: Stanford Rodliff | G89: srodliff3g@ted.com | H89: United States | I89: Lib | J89: L | K89: 2.5 | L89: 36.455 | M89: 182.275 | N89: Liberica | O89: Light
A90: QNA-31113-984 | B90: 43562 | C90: 60512-78550-WS | D90: L-M-0.2 | E90: 4 | F90: Osmund Clausen-Thue | G90: oclausenthue41@marriott.com | H90: United States | I90: Lib | J90: L | K90: 2.5 | L90: 36.455 | M90: 145.82 | N90: Liberica | O90: Light
... A92: DDO-71442-967 | B92: 43567 | C92: 89422-58281-FD | D92: L-D-0.2 | E92: 5 | F92: Alisun Baudino | G92: abaudino5b@netvibes.com | H92: United States | I92: Lib | J92: M | K92: 2.5 | L92: 33.465 | M92: 167.325 | N92: Liberica | O92: Medium
A93: BRV-64870-915 | B93: 43571 | C93: 32070-55528-UG | D93: L-L-2.5 | E93: 5 | F93: Samuele Ales0 | H93: Ireland | I93: Lib | J93: L | K93: 1 | L93: 15.85 | M93: 79.25 | N93: Liberica | O93: Light
A94: NXV-05302-067 | B94: 43577 | C94: 25754-33191-ZI | D94: L-M-2.5 | E94: 4 | F94: Mar McIver | H94: United States | I94: Lib | J94: M | K94: 1 | L94: 14.55 | M94: 58.2 | N94: Liberica | O94: Medium
A95: POF-29666-012 | B95: 43556 | C95: 46885-00260-TL | D95: R-D-0.5 | E95: 1 | F95: Sada Roseborough | G95: sroseboroughr2@virginia.edu | H95: United States | I95: Rob | J95: D | K95: 0.2 | L95: 2.685 | M95: 2.685 | N95: Robusta | O95: Dark
A96: NCH-55389-562 | B96: 43582 | C96: 86579-92122-OC | D96: R-L-2.5 | E96: 2 | F96: Brenn Dundredge | H96: #N/A | I96: Rob | J96: L | K96: 1 | L96: 11.95 | M96: 23.9 | N96: Robusta | O96: Light
A97: XSZ-84273-421 | B97: 43569 | C97: 15405-60469-TM | D97: R-M-0.5 | E97: 3 | F97: Pen Wye | G97: pwye2z@dagondesign.com | H97: United States | I97: Rob | J97: M | K97: 0.2 | L97: 2.985 | M97: 8.955 | N97: Robusta | O97: Medium
A98: LPS-39089-432 | B98: 43579 | C98: 97655-45555-LI | D98: R-D-1 | E98: 5 | F98: Baudoin Alldridge | G98: balldridge93@yandex.ru | H98: United States | I98: Rob | J98: D | K98: 0.5 | L98: 5.37 | M98: 26.85 | N98: Robusta | O98: Dark
A99: AMB-93600-000 | B99: 43599 | C99: 64435-53100-WM | D99: A-L-2.5 | E99: 1 | F99: Tomasina Cotmore | G99: tcotmore9y@amazonaws.com | H99: United States | I99: Ara | J99: L | K99: 1 | L99: 12.95 | M99: 12.95 | N99: Arabica | O99: Light
A100: MOU-74341-266 | B100: 43592 | C100: 99358-65399-TC | D100: A-D-0.5 | E100: 4 | F100: Joshuah Awdry | G100: jawdry9q@utexas.edu | H100: United States | I100: Ara | J100: D | K100: 0.2 | L100: 2.985 | M100: 11.94 | N100: Arabica | O100: Dark
A101: QLM-07145-668 | B101: 43594 | C101: 86437-17399-FK | D101: E-D-0.2 | E101: 2 | F101: Colene Elgey | G101: celgey25@webs.com | H101: United States | I101: Exc | J101: M | K101: 2.5 | L101: 31.625 | M101: 63.25 | N101: Excelsa | O101: Medium
A102: XLD-12920-505 | B102: 43586 | C102: 21907-75962-VB | D102: E-L-0.5 | E102: 6 | F102: Marty Kidstoun | H102: United States | I102: Exc | J102: L | K102: 0.2 | L102: 4.455 | M102: 26.73 | N102: Excelsa | O102: Light
A103: DWZ-69106-473 | B103: 43600 | C103: 76447-50326-IC | D103: L-L-2.5 | E103: 4 | F103: Karry Flanders | G103: kflanders1f@over-blog.com | H103: Ireland | I103: Lib | J103: L | K103: 1 | L103: 15.85 | M103: 63.4 | N103: Liberica | O103: Light
A104: UMT-26130-151 | B104: 43606 | C104: 55864-37682-GQ | D104: L-M-0.2 | E104: 3 | F104: Cecil Weatherall | G104: cweatherallim@toplist.cz | H104: United States | I104: Lib | J104: L | K104: 2.5 | L104: 36.455 | M104: 109.365 | N104: Liberica | O104: Light
A105: QDV-03406-248 | B105: 43608 | C105: 74126-88836-KA | D105: L-M-0.5 | E105: 3 | F105: Stevana Woodham | G105: swoodham3h@businesswire.com | H105: Ireland | I105: Lib | J105: M | K105: 0.2 | L105: 4.365 | M105: 13.095 | N105: Liberica | O105: Medium
A106: MZJ-77284-941 | B106: 43603 | C106: 99978-56910-BN | D106: E-L-0.2 | E106: 5 | F106: Emalee Rolin | G106: erolingq@google.fr | H106: United States | I106: Lib | J106: D | K106: 2.5 | L106: 29.785 | M106: 148.925 | N106: Liberica | O106: Dark
...

Sheet Detail3
A1: Details for Sum of Sales - Months (Order Date): Jul, Years (Order Date): 2019
A3: Order ID | B3: Order Date | C3: Customer ID | D3: Product ID | E3: Quantity | F3: Customer Name | G3: Email | H3: Country | I3: Coffee Type | J3: Roast Type | K3: Size | L3: Unit Price | M3: Sales | N3: Coffee Type name | O3: Roast type Name
A4: GPZ-36017-366 | B4: 43647 | C4: 65732-22589-OW | D4: A-D-2.5 | E4: 5 | F4: Kippie Marrison | G4: kmarrisonoq@dropbox.com | H4: United States | I4: Ara | J4: D | K4: 2.5 | L4: 22.885 | M4: 114.425 | N4: Arabica | O4: Dark
A5: MIU-01481-194 | B5: 43667 | C5: 08439-55669-AI | D5: A-L-0.5 | E5: 2 | F5: Rafferty Pursglove | G5: rpursglovel9@biblegateway.com | H5: United States | I5: Ara | J5: L | K5: 0.5 | L5: 7.77 | M5: 15.54 | N5: Arabica | O5: Light
A6: CQW-37388-302 | B6: 43649 | C6: 97741-98924-KT | D6: A-D-2.5 | E6: 3 | F6: Willabella Harvison | G6: wharvisonjx@gizmodo.com | H6: United States | I6: Ara | J6: D | K6: 2.5 | L6: 22.885 | M6: 68.655 | N6: Arabica | O6: Dark
A7: TBB-29780-459 | B7: 43661 | C7: 61437-83623-PZ | D7: A-L-0.5 | E7: 1 | F7: Vivyan Dunning | G7: vdunningji@independent.co.uk | H7: United States | I7: Ara | J7: L | K7: 0.5 | L7: 7.77 | M7: 7.77 | N7: Arabica | O7: Light
A8: LCB-02099-995 | B8: 43677 | C8: 06757-96251-UH | D8: A-D-0.2 | E8: 6 | F8: Gran Sibray | G8: gsibrayb2@wsj.com | H8: United States | I8: Ara | J8: D | K8: 0.2 | L8: 2.985 | M8: 17.91 | N8: Arabica | O8: Dark
A9: UJQ-54441-340 | B9: 43676 | C9: 26822-19510-SD | D9: A-L-0.2 | E9: 5 | F9: Gabie Tweed | G9: gtweed8v@yolasite.com | H9: United States | I9: Ara | J9: L | K9: 0.2 | L9: 3.885 | M9: 19.425 | N9: Arabica | O9: Light
A10: XXJ-47000-307 | B10: 43664 | C10: 31582-23562-FM | D10: A-D-0.2 | E10: 4 | F10: Jeffrey Dufaire | G10: jdufaire2d@fc2.com | H10: United States | I10: Ara | J10: D | K10: 0.2 | L10: 2.985 | M10: 11.94 | N10: Arabica | O10: Dark
A11: XXJ-47000-307 | B11: 43664 | C11: 31582-23562-FM | D11: A-L-2.5 | E11: 3 | F11: Jeffrey Dufaire | G11: jdufaire2d@fc2.com | H11: United States | I11: Ara | J11: L | K11: 2.5 | L11: 29.785 | M11: 89.355 | N11: Arabica | O11: Light
A12: GVG-59542-307 | B12: 43648 | C12: 26314-66792-VP | D12: E-M-1 | E12: 2 | F12: Bran Sterke | G12: bsterkekw@biblegateway.com | H12: United States | I12: Exc | J12: M | K12: 1 | L12: 13.75 | M12: 27.5 | N12: Excelsa | O12: Medium
A13: UVF-59322-459 | B13: 43671 | C13: 53971-49906-PZ | D13: E-L-2.5 | E13: 6 | F13: Daniel Heinonen | G13: dheinonengd@printfriendly.com | H13: United States | I13: Exc | J13: L | K13: 2.5 | L13: 34.155 | M13: 204.93 | N13: Excelsa | O13: Light
A14: OQS-46321-904 | B14: 43666 | C14: 19597-91185-CM | D14: E-M-1 | E14: 1 | F14: Diena Peetermann | H14: United States | I14: Exc | J14: M | K14: 1 | L14: 13.75 | M14: 13.75 | N14: Excelsa | O14: Medium
A15: UJQ-54441-340 | B15: 43676 | C15: 26822-19510-SD | D15: E-M-0.2 | E15: 2 | F15: Gabie Tweed | G15: gtweed8v@yolasite.com | H15: United States | I15: Exc | J15: M | K15: 0.2 | L15: 4.125 | M15: 8.25 | N15: Excelsa | O15: Medium
A16: OGY-19377-175 | B16: 43655 | C16: 49084-44492-OJ | D16: E-D-0.5 | E16: 1 | F16: Barney Chisnell | H16: Ireland | I16: Exc | J16: D | K16: 0.5 | L16: 7.29 | M16: 7.29 | N16: Excelsa | O16: Dark
A17: CYV-13426-645 | B17: 43652 | C17: 88593-59934-VU | D17: E-D-1 | E17: 1 | F17: Evelina Dacca | G17: edacca3l@google.pl | H17: United States | I17: Exc | J17: D | K17: 1 | L17: 12.15 | M17: 12.15 | N17: Excelsa | O17: Dark
A18: DTB-71371-705 | B18: 43649 | C18: 48544-90737-AZ | D18: L-D-1 | E18: 1 | F18: Chiarra Shalders | G18: cshaldersqx@cisco.com | H18: United States | I18: Lib | J18: D | K18: 1 | L18: 12.95 | M18: 12.95 | N18: Liberica | O18: Dark
A19: VSQ-07182-513 | B19: 43669 | C19: 18366-65239-WF | D19: L-L-0.2 | E19: 6 | F19: Brendan Grece | G19: bgrecefm@naver.com | H19: United Kingdom | I19: Lib | J19: L | K19: 0.2 | L19: 4.755 | M19: 28.53 | N19: Liberica | O19: Light
A20: LRK-97117-150 | B20: 43654 | C20: 33000-22405-LO | D20: L-L-1 | E20: 6 | F20: Sean Lorenzetti | G20: slorenzettidl@is.gd | H20: United States | I20: Lib | J20: L | K20: 1 | L20: 15.85 | M20: 95.1 | N20: Liberica | O20: Light
A21: ZQI-47236-301 | B21: 43671 | C21: 23446-47798-ID | D21: L-L-0.5 | E21: 5 | F21: Carmelita Thowes | G21: cthowescp@craigslist.org | H21: United States | I21: Lib | J21: L | K21: 0.5 | L21: 9.51 | M21: 47.55 | N21: Liberica | O21: Light
A22: HST-96923-073 | B22: 43664 | C22: 54722-76431-EX | D22: R-D-2.5 | E22: 6 | F22: Helli Petroulis | G22: hpetroulisol@state.tx.us | H22: Ireland | I22: Rob | J22: D | K22: 2.5 | L22: 20.585 | M22: 123.51 | N22: Robusta | O22: Dark
A23: MIU-01481-194 | B23: 43667 | C23: 08439-55669-AI | D23: R-M-1 | E23: 6 | F23: Rafferty Pursglove | G23: rpursglovel9@biblegateway.com | H23: United States | I23: Rob | J23: M | K23: 1 | L23: 9.95 | M23: 59.7 | N23: Robusta | O23: Medium
A24: JQT-14347-517 | B24: 43672 | C24: 11621-09964-ID | D24: R-D-1 | E24: 1 | F24: Lorelei Nardoni | G24: lnardonil2@hao123.com | H24: United States | I24: Rob | J24: D | K24: 1 | L24: 8.95 | M24: 8.95 | N24: Robusta | O24: Dark
A25: AXN-57779-891 | B25: 43660 | C25: 09668-23340-IC | D25: R-M-0.2 | E25: 3 | F25: Donavon Fowle | G25: dfowlegr@epa.gov | H25: United States | I25: Rob | J25: M | K25: 0.2 | L25: 2.985 | M25: 8.955 | N25: Robusta | O25: Medium

Sheet Dashboard
AB12: ;

Sheet TotalSales
A3: Sum of Sales | C3: Coffee Type name
A4: Years (Order Date) | B4: Months (Order Date) | C4: Arabica | D4: Excelsa | E4: Liberica | F4: Robusta | G4: Grand Total
A5: 2019 | B5: Jan | C5: 186.855 | D5: 305.97 | E5: 213.16 | F5: 123 | G5: 828.985
B6: Feb | C6: 251.965 | D6: 129.46 | E6: 434.04 | F6: 171.94 | G6: 987.405
B7: Mar | C7: 224.945 | D7: 349.12 | E7: 321.04 | F7: 126.035 | G7: 1021.14
B8: Apr | C8: 307.12 | D8: 681.075 | E8: 533.705 | F8: 158.85 | G8: 1680.75
B9: May | C9: 53.665 | D9: 83.025 | E9: 193.835 | F9: 68.04 | G9: 398.565
B10: Jun | C10: 163.02 | D10: 678.36 | E10: 171.045 | F10: 372.255 | G10: 1384.68
B11: Jul | C11: 345.02 | D11: 273.87 | E11: 184.13 | F11: 201.115 | G11: 1004.135
B12: Aug | C12: 334.89 | D12: 70.95 | E12: 134.23 | F12: 166.275 | G12: 706.345
B13: Sep | C13: 178.71 | D13: 166.1 | E13: 439.31 | F13: 492.9 | G13: 1277.02
B14: Oct | C14: 301.985 | D14: 153.765 | E14: 215.555 | F14: 213.665 | G14: 884.97
B15: Nov | C15: 312.835 | D15: 63.25 | E15: 350.895 | F15: 96.405 | G15: 823.385
B16: Dec | C16: 265.62 | D16: 526.515 | E16: 187.06 | F16: 210.59 | G16: 1189.785
A17: 2019 Total | C17: 2926.63 | D17: 3481.46 | E17: 3378.005 | F17: 2401.07 | G17: 12187.165
A18: 2020 | B18: Jan | C18: 47.25 | D18: 65.805 | E18: 274.675 | F18: 179.22 | G18: 566.95
B19: Feb | C19: 745.45 | D19: 428.885 | E19: 194.175 | F19: 429.83 | G19: 1798.34
B20: Mar | C20: 130.47 | D20: 271.485 | E20: 281.205 | F20: 231.63 | G20: 914.79
B21: Apr | C21: 27 | D21: 347.26 | E21: 147.51 | F21: 240.04 | G21: 761.81
B22: May | C22: 255.115 | D22: 541.73 | E22: 83.43 | F22: 59.08 | G22: 939.355
B23: Jun | C23: 584.79 | D23: 357.43 | E23: 355.34 | F23: 140.88 | G23: 1438.44
B24: Jul | C24: 430.62 | D24: 227.425 | E24: 236.315 | F24: 414.585 | G24: 1308.945
B25: Aug | C25: 22.5 | D25: 77.72 | E25: 60.5 | F25: 139.68 | G25: 300.4
B26: Sep | C26: 126.15 | D26: 195.11 | E26: 89.13 | F26: 302.66 | G26: 713.05
B27: Oct | C27: 376.03 | D27: 523.24 | E27: 440.965 | F27: 174.47 | G27: 1514.705
B28: Nov | C28: 515.18 | D28: 142.56 | E28: 347.04 | F28: 104.085 | G28: 1108.865
B29: Dec | C29: 95.86 | D29: 484.76 | E29: 94.17 | F29: 77.105 | G29: 751.895
A30: 2020 Total | C30: 3356.415 | D30: 3663.41 | E30: 2604.455 | F30: 2493.265 | G30: 12117.545
A31: 2021 | B31: Jan | C31: 258.345 | D31: 139.625 | E31: 279.52 | F31: 160.195 | G31: 837.685
B32: Feb | C32: 342.2 | D32: 284.25 | E32: 251.83 | F32: 80.55 | G32: 958.83
B33: Mar | C33: 418.305 | D33: 468.125 | E33: 405.055 | F33: 253.155 | G33: 1544.64
B34: Apr | C34: 102.33 | D34: 242.14 | E34: 554.875 | F34: 106.24 | G34: 1005.585
B35: May | C35: 234.72 | D35: 133.08 | E35: 267.2 | F35: 272.69 | G35: 907.69
B36: Jun | C36: 430.39 | D36: 136.205 | E36: 209.6 | F36: 88.335 | G36: 864.53
B37: Jul | C37: 109.005 | D37: 393.575 | E37: 61.035 | F37: 199.49 | G37: 763.105
B38: Aug | C38: 287.525 | D38: 288.67 | E38: 125.58 | F38: 374.135 | G38: 1075.91
B39: Sep | C39: 840.93 | D39: 409.875 | E39: 171.33 | F39: 221.44 | G39: 1643.575
B40: Oct | C40: 299.07 | D40: 260.325 | E40: 584.64 | F40: 256.365 | G40: 1400.4
B41: Nov | C41: 323.325 | D41: 565.57 | E41: 537.81 | F41: 189.475 | G41: 1616.18
B42: Dec | C42: 399.485 | D42: 148.2 | E42: 388.22 | F42: 212.075 | G42: 1147.98
A43: 2021 Total | C43: 4045.63 | D43: 3469.64 | E43: 3836.695 | F43: 2414.145 | G43: 13766.11
A44: 2022 | B44: Jan | C44: 112.695 | D44: 166.32 | E44: 843.715 | F44: 146.685 | G44: 1269.415
B45: Feb | C45: 114.88 | D45: 133.815 | E45: 91.175 | F45: 53.76 | G45: 393.63
B46: Mar | C46: 277.76 | D46: 175.41 | E46: 462.51 | F46: 399.525 | G46: 1315.205
B47: Apr | C47: 197.895 | D47: 289.755 | E47: 88.545 | F47: 200.255 | G47: 776.45
B48: May | C48: 193.115 | D48: 212.495 | E48: 292.29 | F48: 304.47 | G48: 1002.37
B49: Jun | C49: 179.79 | D49: 426.2 | E49: 170.09 | F49: 379.31 | G49: 1155.39
B50: Jul | C50: 247.29 | D50: 246.685 | E50: 271.055 | F50: 141.7 | G50: 906.73
B51: Aug | C51: 116.395 | D51: 41.25 | E51: 15.54 | F51: 71.06 | G51: 244.245
A52: 2022 Total | C52: 1439.82 | D52: 1691.93 | E52: 2234.92 | F52: 1696.765 | G52: 7063.435
A53: Grand Total | C53: 11768.495 | D53: 12306.44 | E53: 12054.075 | F53: 9005.245 | G53: 45134.255

Sheet CountryBar Chart
A3: Country | B3: Sum of Sales
A4: United Kingdom | B4: 2798.505
A5: Ireland | B5: 6696.865
A6: United States | B6: 35638.885
A7: Grand Total | B7: 45134.255

Sheet Top5Customers
A3: Customer Name | B3: Sum of Sales
A4: Don Flintiff | B4: 278.01
A5: Nealson Cuttler | B5: 281.675
A6: Terri Farra | B6: 289.11
A7: Brenn Dundredge | B7: 307.045
A8: Allis Wilmore | B8: 317.07
A9: Grand Total | B9: 1472.91

Sheet orders
A1: Order ID | B1: Order Date | C1: Customer ID | D1: Product ID | E1: Quantity | F1: Customer Name | G1: Email | H1: Country | I1: Coffee Type | J1: Roast Type | K1: Size | L1: Unit Price | M1: Sales | N1: Coffee Type name | O1: Roast type Name | P1: Loyalty Card
A2: QEV-37451-860 | B2: 43713 | C2: 17670-51384-MA | D2: R-M-1 | E2: 2 | F2: =_xlfn.XLOOKUP(orders!C2,customers!$A$1:$A$1001,customers!$B$1:$B$1001,,0) -> Aloisia Allner | G2: =IF(_xlfn.XLOOKUP(orders!C2,customers!$A$1:$A$1001,customers!$C$1:$C$1001,,0)=0,"",_xlfn.XLOOKUP(orders!C2,customers!$A$1:$A$1001,customers!$C$1:$C$1001,,0)) -> aallner0@lulu.com | H2: =_xlfn.XLOOKUP(C2,customers!$A$1:$A$1001,customers!$G$1:$G$1001,,0) -> United States | I2: =INDEX(products!$A$1:$G$49,MATCH(orders!$D2,products!$A$1:$A$49,0),MATCH(orders!I$1,products!$A$1:$G$1,0)) -> Rob | J2: =INDEX(products!$A$1:$G$49,MATCH(orders!$D2,products!$A$1:$A$49,0),MATCH(orders!J$1,products!$A$1:$G$1,0)) -> M | K2: =INDEX(products!$A$1:$G$49,MATCH(orders!$D2,products!$A$1:$A$49,0),MATCH(orders!K$1,products!$A$1:$G$1,0)) -> 1 | L2: =INDEX(products!$A$1:$G$49,MATCH(orders!$D2,products!$A$1:$A$49,0),MATCH(orders!L$1,products!$A$1:$G$1,0)) -> 9.95 | M2: =L2*E2 -> 19.9 | N2: =IF(I2="Rob","Robusta",IF(I2="Exc","Excelsa",IF(I2="Ara","Arabica",IF(I2="Lib","Liberica","")))) -> Robusta | O2: =IF(J2="M","Medium",IF(J2="L","Light",IF(J2="D","Dark",""))) -> Medium | P2: =_xlfn.XLOOKUP(Orders[[#This Row],[Customer ID]],customers!$A$1:$A$1001,customers!$I$1:$I$1001,,0) -> Yes
A3: QEV-37451-860 | B3: 43713 | C3: 17670-51384-MA | D3: E-M-0.5 | E3: 5 | F3: =_xlfn.XLOOKUP(orders!C3,customers!$A$1:$A$1001,customers!$B$1:$B$1001,,0) -> Aloisia Allner | G3: =IF(_xlfn.XLOOKUP(orders!C3,customers!$A$1:$A$1001,customers!$C$1:$C$1001,,0)=0,"",_xlfn.XLOOKUP(orders!C3,customers!$A$1:$A$1001,customers!$C$1:$C$1001,,0)) -> aallner0@lulu.com | H3: =_xlfn.XLOOKUP(C3,customers!$A$1:$A$1001,customers!$G$1:$G$1001,,0) -> United States | I3: =INDEX(products!$A$1:$G$49,MATCH(orders!$D3,products!$A$1:$A$49,0),MATCH(orders!I$1,products!$A$1:$G$1,0)) -> Exc | J3: =INDEX(products!$A$1:$G$49,MATCH(orders!$D3,products!$A$1:$A$49,0),MATCH(orders!J$1,products!$A$1:$G$1,0)) -> M | K3: =INDEX(products!$A$1:$G$49,MATCH(orders!$D3,products!$A$1:$A$49,0),MATCH(orders!K$1,products!$A$1:$G$1,0)) -> 0.5 | L3: =INDEX(products!$A$1:$G$49,MATCH(orders!$D3,products!$A$1:$A$49,0),MATCH(orders!L$1,products!$A$1:$G$1,0)) -> 8.25 | M3: =L3*E3 -> 41.25 | N3: =IF(I3="Rob","Robusta",IF(I3="Exc","Excelsa",IF(I3="Ara","Arabica",IF(I3="Lib","Liberica","")))) -> Excelsa | O3: =IF(J3="M","Medium",IF(J3="L","Light",IF(J3="D","Dark",""))) -> Medium | P3: Yes
A4: FAA-43335-268 | B4: 44364 | C4: 21125-22134-PX | D4: A-L-1 | E4: 1 | F4: =_xlfn.XLOOKUP(orders!C4,customers!$A$1:$A$1001,customers!$B$1:$B$1001,,0) -> Jami Redholes | G4: =IF(_xlfn.XLOOKUP(orders!C4,customers!$A$1:$A$1001,customers!$C$1:$C$1001,,0)=0,"",_xlfn.XLOOKUP(orders!C4,customers!$A$1:$A$1001,customers!$C$1:$C$1001,,0)) -> jredholes2@tmall.com | H4: =_xlfn.XLOOKUP(C4,customers!$A$1:$A$1001,customers!$G$1:$G$1001,,0) -> United States | I4: =INDEX(products!$A$1:$G$49,MATCH(orders!$D4,products!$A$1:$A$49,0),MATCH(orders!I$1,products!$A$1:$G$1,0)) -> Ara | J4: =INDEX(products!$A$1:$G$49,MATCH(orders!$D4,products!$A$1:$A$49,0),MATCH(orders!J$1,products!$A$1:$G$1,0)) -> L | K4: =INDEX(products!$A$1:$G$49,MATCH(orders!$D4,products!$A$1:$A$49,0),MATCH(orders!K$1,products!$A$1:$G$1,0)) -> 1 | L4: =INDEX(products!$A$1:$G$49,MATCH(orders!$D4,products!$A$1:$A$49,0),MATCH(orders!L$1,products!$A$1:$G$1,0)) -> 12.95 | M4: =L4*E4 -> 12.95 | N4: =IF(I4="Rob","Robusta",IF(I4="Exc","Excelsa",IF(I4="Ara","Arabica",IF(I4="Lib","Liberica","")))) -> Arabica | O4: =IF(J4="M","Medium",IF(J4="L","Light",IF(J4="D","Dark",""))) -> Light | P4: =_xlfn.XLOOKUP(Orders[[#This Row],[Customer ID]],customers!$A$1:$A$1001,customers!$I$1:$I$1001,,0) -> Yes
A5: KAC-83089-793 | B5: 44392 | C5: 23806-46781-OU | D5: E-M-1 | E5: 2 | F5: =_xlfn.XLOOKUP(orders!C5,customers!$A$1:$A$1001,customers!$B$1:$B$1001,,0) -> Christoffer O' Shea | G5: =IF(_xlfn.XLOOKUP(orders!C5,customers!$A$1:$A$1001,customers!$C$1:$C$1001,,0)=0,"",_xlfn.XLOOKUP(orders!C5,customers!$A$1:$A$1001,customers!$C$1:$C$1001,,0)) | H5: =_xlfn.XLOOKUP(C5,customers!$A$1:$A$1001,customers!$G$1:$G$1001,,0) -> Ireland | I5: =INDEX(products!$A$1:$G$49,MATCH(orders!$D5,products!$A$1:$A$49,0),MATCH(orders!I$1,products!$A$1:$G$1,0)) -> Exc | J5: =INDEX(products!$A$1:$G$49,MATCH(orders!$D5,products!$A$1:$A$49,0),MATCH(orders!J$1,products!$A$1:$G$1,0)) -> M | K5: =INDEX(products!$A$1:$G$49,MATCH(orders!$D5,products!$A$1:$A$49,0),MATCH(orders!K$1,products!$A$1:$G$1,0)) -> 1 | L5: =INDEX(products!$A$1:$G$49,MATCH(orders!$D5,products!$A$1:$A$49,0),MATCH(orders!L$1,products!$A$1:$G$1,0)) -> 13.75 | M5: =L5*E5 -> 27.5 | N5: =IF(I5="Rob","Robusta",IF(I5="Exc","Excelsa",IF(I5="Ara","Arabica",IF(I5="Lib","Liberica","")))) -> Excelsa | O5: =IF(J5="M","Medium",IF(J5="L","Light",IF(J5="D","Dark",""))) -> Medium | P5: =_xlfn.XLOOKUP(Orders[[#This Row],[Customer ID]],customers!$A$1:$A$1001,customers!$I$1:$I$1001,,0) -> No
A6: KAC-83089-793 | B6: 44392 | C6: 23806-46781-OU | D6: R-L-2.5 | E6: 2 | F6: =_xlfn.XLOOKUP(orders!C6,customers!$A$1:$A$1001,customers!$B$1:$B$1001,,0) -> Christoffer O' Shea | G6: =IF(_xlfn.XLOOKUP(orders!C6,customers!$A$1:$A$1001,customers!$C$1:$C$1001,,0)=0,"",_xlfn.XLOOKUP(orders!C6,customers!$A$1:$A$1001,customers!$C$1:$C$1001,,0)) | H6: =_xlfn.XLOOKUP(C6,customers!$A$1:$A$1001,customers!$G$1:$G$1001,,0) -> Ireland | I6: =INDEX(products!$A$1:$G$49,MATCH(orders!$D6,products!$A$1:$A$49,0),MATCH(orders!I$1,products!$A$1:$G$1,0)) -> Rob | J6: =INDEX(products!$A$1:$G$49,MATCH(orders!$D6,products!$A$1:$A$49,0),MATCH(orders!J$1,products!$A$1:$G$1,0)) -> L | K6: =INDEX(products!$A$1:$G$49,MATCH(orders!$D6,products!$A$1:$A$49,0),MATCH(orders!K$1,products!$A$1:$G$1,0)) -> 2.5 | L6: =INDEX(products!$A$1:$G$49,MATCH(orders!$D6,products!$A$1:$A$49,0),MATCH(orders!L$1,products!$A$1:$G$1,0)) -> 27.485 | M6: =L6*E6 -> 54.97 | N6: =IF(I6="Rob","Robusta",IF(I6="Exc","Excelsa",IF(I6="Ara","Arabica",IF(I6="Lib","Liberica","")))) -> Robusta | O6: =IF(J6="M","Medium",IF(J6="L","Light",IF(J6="D","Dark",""))) -> Light | P6: =_xlfn.XLOOKUP(Orders[[#This Row],[Customer ID]],customers!$A$1:$A$1001,customers!$I$1:$I$1001,,0) -> No
A7: CVP-18956-553 | B7: 44412 | C7: 86561-91660-RB | D7: L-D-1 | E7: 3 | F7: =_xlfn.XLOOKUP(orders!C7,customers!$A$1:$A$1001,customers!$B$1:$B$1001,,0) -> Beryle Cottier | G7: =IF(_xlfn.XLOOKUP(orders!C7,customers!$A$1:$A$1001,customers!$C$1:$C$1001,,0)=0,"",_xlfn.XLOOKUP(orders!C7,customers!$A$1:$A$1001,customers!$C$1:$C$1001,,0)) | H7: =_xlfn.XLOOKUP(C7,customers!$A$1:$A$1001,customers!$G$1:$G$1001,,0) -> United States | I7: =INDEX(products!$A$1:$G$49,MATCH(orders!$D7,products!$A$1:$A$49,0),MATCH(orders!I$1,products!$A$1:$G$1,0)) -> Lib | J7: =INDEX(products!$A$1:$G$49,MATCH(orders!$D7,products!$A$1:$A$49,0),MATCH(orders!J$1,products!$A$1:$G$1,0)) -> D | K7: =INDEX(products!$A$1:$G$49,MATCH(orders!$D7,products!$A$1:$A$49,0),MATCH(orders!K$1,products!$A$1:$G$1,0)) -> 1 | L7: =INDEX(products!$A$1:$G$49,MATCH(orders!$D7,products!$A$1:$A$49,0),MATCH(orders!L$1,products!$A$1:$G$1,0)) -> 12.95 | M7: =L7*E7 -> 38.85 | N7: =IF(I7="Rob","Robusta",IF(I7="Exc","Excelsa",IF(I7="Ara","Arabica",IF(I7="Lib","Liberica","")))) -> Liberica | O7: =IF(J7="M","Medium",IF(J7="L","Light",IF(J7="D","Dark",""))) -> Dark | P7: =_xlfn.XLOOKUP(Orders[[#This Row],[Customer ID]],customers!$A$1:$A$1001,customers!$I$1:$I$1001,,0) -> No
A8: IPP-31994-879 | B8: 44582 | C8: 65223-29612-CB | D8: E-D-0.5 | E8: 3 | F8: =_xlfn.XLOOKUP(orders!C8,customers!$A$1:$A$1001,customers!$B$1:$B$1001,,0) -> Shaylynn Lobe | G8: =IF(_xlfn.XLOOKUP(orders!C8,customers!$A$1:$A$1001,customers!$C$1:$C$1001,,0)=0,"",_xlfn.XLOOKUP(orders!C8,customers!$A$1:$A$1001,customers!$C$1:$C$1001,,0)) -> slobe6@nifty.com | H8: =_xlfn.XLOOKUP(C8,customers!$A$1:$A$1001,customers!$G$1:$G$1001,,0) -> United States | I8: =INDEX(products!$A$1:$G$49,MATCH(orders!$D8,products!$A$1:$A$49,0),MATCH(orders!I$1,products!$A$1:$G$1,0)) -> Exc | J8: =INDEX(products!$A$1:$G$49,MATCH(orders!$D8,products!$A$1:$A$49,0),MATCH(orders!J$1,products!$A$1:$G$1,0)) -> D | K8: =INDEX(products!$A$1:$G$49,MATCH(orders!$D8,products!$A$1:$A$49,0),MATCH(orders!K$1,products!$A$1:$G$1,0)) -> 0.5 | L8: =INDEX(products!$A$1:$G$49,MATCH(orders!$D8,products!$A$1:$A$49,0),MATCH(orders!L$1,products!$A$1:$G$1,0)) -> 7.29 | M8: =L8*E8 -> 21.87 | N8: =IF(I8="Rob","Robusta",IF(I8="Exc","Excelsa",IF(I8="Ara","Arabica",IF(I8="Lib","Liberica","")))) -> Excelsa | O8: =IF(J8="M","Medium",IF(J8="L","Light",IF(J8="D","Dark",""))) -> Dark | P8: =_xlfn.XLOOKUP(Orders[[#This Row],[Customer ID]],customers!$A$1:$A$1001,customers!$I$1:$I$1001,,0) -> Yes
A9: SNZ-65340-705 | B9: 44701 | C9: 21134-81676-FR | D9: L-L-0.2 | E9: 1 | F9: =_xlfn.XLOOKUP(orders!C9,customers!$A$1:$A$1001,customers!$B$1:$B$1001,,0) -> Melvin Wharfe | G9: =IF(_xlfn.XLOOKUP(orders!C9,customers!$A$1:$A$1001,customers!$C$1:$C$1001,,0)=0,"",_xlfn.XLOOKUP(orders!C9,customers!$A$1:$A$1001,customers!$C$1:$C$1001,,0)) | H9: =_xlfn.XLOOKUP(C9,customers!$A$1:$A$1001,customers!$G$1:$G$1001,,0) -> Ireland | I9: =INDEX(products!$A$1:$G$49,MATCH(orders!$D9,products!$A$1:$A$49,0),MATCH(orders!I$1,products!$A$1:$G$1,0)) -> Lib | J9: =INDEX(products!$A$1:$G$49,MATCH(orders!$D9,products!$A$1:$A$49,0),MATCH(orders!J$1,products!$A$1:$G$1,0)) -> L | K9: =INDEX(products!$A$1:$G$49,MATCH(orders!$D9,products!$A$1:$A$49,0),MATCH(orders!K$1,products!$A$1:$G$1,0)) -> 0.2 | L9: =INDEX(products!$A$1:$G$49,MATCH(orders!$D9,products!$A$1:$A$49,0),MATCH(orders!L$1,products!$A$1:$G$1,0)) -> 4.755 | M9: =L9*E9 -> 4.755 | N9: =IF(I9="Rob","Robusta",IF(I9="Exc","Excelsa",IF(I9="Ara","Arabica",IF(I9="Lib","Liberica","")))) -> Liberica | O9: =IF(J9="M","Medium",IF(J9="L","Light",IF(J9="D","Dark",""))) -> Light | P9: =_xlfn.XLOOKUP(Orders[[#This Row],[Customer ID]],customers!$A$1:$A$1001,customers!$I$1:$I$1001,,0) -> Yes
A10: EZT-46571-659 | B10: 43467 | C10: 03396-68805-ZC | D10: R-M-0.5 | E10: 3 | F10: =_xlfn.XLOOKUP(orders!C10,customers!$A$1:$A$1001,customers!$B$1:$B$1001,,0) -> Guthrey Petracci | G10: =IF(_xlfn.XLOOKUP(orders!C10,customers!$A$1:$A$1001,customers!$C$1:$C$1001,,0)=0,"",_xlfn.XLOOKUP(orders!C10,customers!$A$1:$A$1001,customers!$C$1:$C$1001,,0)) -> gpetracci8@livejournal.com | H10: =_xlfn.XLOOKUP(C10,customers!$A$1:$A$1001,customers!$G$1:$G$1001,,0) -> United States | I10: =INDEX(products!$A$1:$G$49,MATCH(orders!$D10,products!$A$1:$A$49,0),MATCH(orders!I$1,products!$A$1:$G$1,0)) -> Rob | J10: =INDEX(products!$A$1:$G$49,MATCH(orders!$D10,products!$A$1:$A$49,0),MATCH(orders!J$1,products!$A$1:$G$1,0)) -> M | K10: =INDEX(products!$A$1:$G$49,MATCH(orders!$D10,products!$A$1:$A$49,0),MATCH(orders!K$1,products!$A$1:$G$1,0)) -> 0.5 | L10: =INDEX(products!$A$1:$G$49,MATCH(orders!$D10,products!$A$1:$A$49,0),MATCH(orders!L$1,products!$A$1:$G$1,0)) -> 5.97 | M10: =L10*E10 -> 17.91 | N10: =IF(I10="Rob","Robusta",IF(I10="Exc","Excelsa",IF(I10="Ara","Arabica",IF(I10="Lib","Liberica","")))) -> Robusta | O10: =IF(J10="M","Medium",IF(J10="L","Light",IF(J10="D","Dark",""))) -> Medium | P10: =_xlfn.XLOOKUP(Orders[[#This Row],[Customer ID]],customers!$A$1:$A$1001,customers!$I$1:$I$1001,,0) -> No
A11: NWQ-70061-912 | B11: 43713 | C11: 61021-27840-ZN | D11: R-M-0.5 | E11: 1 | F11: =_xlfn.XLOOKUP(orders!C11,customers!$A$1:$A$1001,customers!$B$1:$B$1001,,0) -> Rodger Raven | G11: =IF(_xlfn.XLOOKUP(orders!C11,customers!$A$1:$A$1001,customers!$C$1:$C$1001,,0)=0,"",_xlfn.XLOOKUP(orders!C11,customers!$A$1:$A$1001,customers!$C$1:$C$1001,,0)) -> rraven9@ed.gov | H11: =_xlfn.XLOOKUP(C11,customers!$A$1:$A$1001,customers!$G$1:$G$1001,,0) -> United States | I11: =INDEX(products!$A$1:$G$49,MATCH(orders!$D11,products!$A$1:$A$49,0),MATCH(orders!I$1,products!$A$1:$G$1,0)) -> Rob | J11: =INDEX(products!$A$1:$G$49,MATCH(orders!$D11,products!$A$1:$A$49,0),MATCH(orders!J$1,products!$A$1:$G$1,0)) -> M | K11: =INDEX(products!$A$1:$G$49,MATCH(orders!$D11,products!$A$1:$A$49,0),MATCH(orders!K$1,products!$A$1:$G$1,0)) -> 0.5 | L11: =INDEX(products!$A$1:$G$49,MATCH(orders!$D11,products!$A$1:$A$49,0),MATCH(orders!L$1,products!$A$1:$G$1,0)) -> 5.97 | M11: =L11*E11 -> 5.97 | N11: =IF(I11="Rob","Robusta",IF(I11="Exc","Excelsa",IF(I11="Ara","Arabica",IF(I11="Lib","Liberica","")))) -> Robusta | O11: =IF(J11="M","Medium",IF(J11="L","Light",IF(J11="D","Dark",""))) -> Medium | P11: =_xlfn.XLOOKUP(Orders[[#This Row],[Customer ID]],customers!$A$1:$A$1001,customers!$I$1:$I$1001,,0) -> No
A12: BKK-47233-845 | B12: 44263 | C12: 76239-90137-UQ | D12: A-D-1 | E12: 4 | F12: =_xlfn.XLOOKUP(orders!C12,customers!$A$1:$A$1001,customers!$B$1:$B$1001,,0) -> Ferrell Ferber | G12: =IF(_xlfn.XLOOKUP(orders!C12,customers!$A$1:$A$1001,customers!$C$1:$C$1001,,0)=0,"",_xlfn.XLOOKUP(orders!C12,customers!$A$1:$A$1001,customers!$C$1:$C$1001,,0)) -> fferbera@businesswire.com | H12: =_xlfn.XLOOKUP(C12,customers!$A$1:$A$1001,customers!$G$1:$G$1001,,0) -> United States | I12: =INDEX(products!$A$1:$G$49,MATCH(orders!$D12,products!$A$1:$A$49,0),MATCH(orders!I$1,products!$A$1:$G$1,0)) -> Ara | J12: =INDEX(products!$A$1:$G$49,MATCH(orders!$D12,products!$A$1:$A$49,0),MATCH(orders!J$1,products!$A$1:$G$1,0)) -> D | K12: =INDEX(products!$A$1:$G$49,MATCH(orders!$D12,products!$A$1:$A$49,0),MATCH(orders!K$1,products!$A$1:$G$1,0)) -> 1 | L12: =INDEX(products!$A$1:$G$49,MATCH(orders!$D12,products!$A$1:$A$49,0),MATCH(orders!L$1,products!$A$1:$G$1,0)) -> 9.95 | M12: =L12*E12 -> 39.8 | N12: =IF(I12="Rob","Robusta",IF(I12="Exc","Excelsa",IF(I12="Ara","Arabica",IF(I12="Lib","Liberica","")))) -> Arabica | O12: =IF(J12="M","Medium",IF(J12="L","Light",IF(J12="D","Dark",""))) -> Dark | P12: =_xlfn.XLOOKUP(Orders[[#This Row],[Customer ID]],customers!$A$1:$A$1001,customers!$I$1:$I$1001,,0) -> No
A13: VQR-01002-970 | B13: 44132 | C13: 49315-21985-BB | D13: E-L-2.5 | E13: 5 | F13: =_xlfn.XLOOKUP(orders!C13,customers!$A$1:$A$1001,customers!$B$1:$B$1001,,0) -> Duky Phizackerly | G13: =IF(_xlfn.XLOOKUP(orders!C13,customers!$A$1:$A$1001,customers!$C$1:$C$1001,,0)=0,"",_xlfn.XLOOKUP(orders!C13,customers!$A$1:$A$1001,customers!$C$1:$C$1001,,0)) -> dphizackerlyb@utexas.edu | H13: =_xlfn.XLOOKUP(C13,customers!$A$1:$A$1001,customers!$G$1:$G$1001,,0) -> United States | I13: =INDEX(products!$A$1:$G$49,MATCH(orders!$D13,products!$A$1:$A$49,0),MATCH(orders!I$1,products!$A$1:$G$1,0)) -> Exc | J13: =INDEX(products!$A$1:$G$49,MATCH(orders!$D13,products!$A$1:$A$49,0),MATCH(orders!J$1,products!$A$1:$G$1,0)) -> L | K13: =INDEX(products!$A$1:$G$49,MATCH(orders!$D13,products!$A$1:$A$49,0),MATCH(orders!K$1,products!$A$1:$G$1,0)) -> 2.5 | L13: =INDEX(products!$A$1:$G$49,MATCH(orders!$D13,products!$A$1:$A$49,0),MATCH(orders!L$1,products!$A$1:$G$1,0)) -> 34.155 | M13: =L13*E13 -> 170.775 | N13: =IF(I13="Rob","Robusta",IF(I13="Exc","Excelsa",IF(I13="Ara","Arabica",IF(I13="Lib","Liberica","")))) -> Excelsa | O13: =IF(J13="M","Medium",IF(J13="L","Light",IF(J13="D","Dark",""))) -> Light | P13: =_xlfn.XLOOKUP(Orders[[#This Row],[Customer ID]],customers!$A$1:$A$1001,customers!$I$1:$I$1001,,0) -> Yes
A14: SZW-48378-399 | B14: 44744 | C14: 34136-36674-OM | D14: R-M-1 | E14: 5 | F14: =_xlfn.XLOOKUP(orders!C14,customers!$A$1:$A$1001,customers!$B$1:$B$1001,,0) -> Rosaleen Scholar | G14: =IF(_xlfn.XLOOKUP(orders!C14,customers!$A$1:$A$1001,customers!$C$1:$C$1001,,0)=0,"",_xlfn.XLOOKUP(orders!C14,customers!$A$1:$A$1001,customers!$C$1:$C$1001,,0)) -> rscholarc@nyu.edu | H14: =_xlfn.XLOOKUP(C14,customers!$A$1:$A$1001,customers!$G$1:$G$1001,,0) -> United States | I14: =INDEX(products!$A$1:$G$49,MATCH(orders!$D14,products!$A$1:$A$49,0),MATCH(orders!I$1,products!$A$1:$G$1,0)) -> Rob | J14: =INDEX(products!$A$1:$G$49,MATCH(orders!$D14,products!$A$1:$A$49,0),MATCH(orders!J$1,products!$A$1:$G$1,0)) -> M | K14: =INDEX(products!$A$1:$G$49,MATCH(orders!$D14,products!$A$1:$A$49,0),MATCH(orders!K$1,products!$A$1:$G$1,0)) -> 1 | L14: =INDEX(products!$A$1:$G$49,MATCH(orders!$D14,products!$A$1:$A$49,0),MATCH(orders!L$1,products!$A$1:$G$1,0)) -> 9.95 | M14: =L14*E14 -> 49.75 | N14: =IF(I14="Rob","Robusta",IF(I14="Exc","Excelsa",IF(I14="Ara","Arabica",IF(I14="Lib","Liberica","")))) -> Robusta | O14: =IF(J14="M","Medium",IF(J14="L","Light",IF(J14="D","Dark",""))) -> Medium | P14: =_xlfn.XLOOKUP(Orders[[#This Row],[Customer ID]],customers!$A$1:$A$1001,customers!$I$1:$I$1001,,0) -> No
A15: ITA-87418-783 | B15: 43973 | C15: 39396-12890-PE | D15: R-D-2.5 | E15: 2 | F15: =_xlfn.XLOOKUP(orders!C15,customers!$A$1:$A$1001,customers!$B$1:$B$1001,,0) -> Terence Vanyutin | G15: =IF(_xlfn.XLOOKUP(orders!C15,customers!$A$1:$A$1001,customers!$C$1:$C$1001,,0)=0,"",_xlfn.XLOOKUP(orders!C15,customers!$A$1:$A$1001,customers!$C$1:$C$1001,,0)) -> tvanyutind@wix.com | H15: =_xlfn.XLOOKUP(C15,customers!$A$1:$A$1001,customers!$G$1:$G$1001,,0) -> United States | I15: =INDEX(products!$A$1:$G$49,MATCH(orders!$D15,products!$A$1:$A$49,0),MATCH(orders!I$1,products!$A$1:$G$1,0)) -> Rob | J15: =INDEX(products!$A$1:$G$49,MATCH(orders!$D15,products!$A$1:$A$49,0),MATCH(orders!J$1,products!$A$1:$G$1,0)) -> D | K15: =INDEX(products!$A$1:$G$49,MATCH(orders!$D15,products!$A$1:$A$49,0),MATCH(orders!K$1,products!$A$1:$G$1,0)) -> 2.5 | L15: =INDEX(products!$A$1:$G$49,MATCH(orders!$D15,products!$A$1:$A$49,0),MATCH(orders!L$1,products!$A$1:$G$1,0)) -> 20.585 | M15: =L15*E15 -> 41.17 | N15: =IF(I15="Rob","Robusta",IF(I15="Exc","Excelsa",IF(I15="Ara","Arabica",IF(I15="Lib","Liberica","")))) -> Robusta | O15: =IF(J15="M","Medium",IF(J15="L","Light",IF(J15="D","Dark",""))) -> Dark | P15: =_xlfn.XLOOKUP(Orders[[#This Row],[Customer ID]],customers!$A$1:$A$1001,customers!$I$1:$I$1001,,0) -> No
... A1001: IRV-20769-219 | B1001: 44119 | C1001: 77131-58092-GE | D1001: E-M-0.2 | E1001: 3 | F1001: =_xlfn.XLOOKUP(orders!C1001,customers!$A$1:$A$1001,customers!$B$1:$B$1001,,0) -> Vidovic Antonelli | G1001: =IF(_xlfn.XLOOKUP(orders!C1001,customers!$A$1:$A$1001,customers!$C$1:$C$1001,,0)=0,"",_xlfn.XLOOKUP(orders!C1001,customers!$A$1:$A$1001,customers!$C$1:$C$1001,,0)) | H1001: =_xlfn.XLOOKUP(C1001,customers!$A$1:$A$1001,customers!$G$1:$G$1001,,0) -> United Kingdom | I1001: =INDEX(products!$A$1:$G$49,MATCH(orders!$D1001,products!$A$1:$A$49,0),MATCH(orders!I$1,products!$A$1:$G$1,0)) -> Exc | J1001: =INDEX(products!$A$1:$G$49,MATCH(orders!$D1001,products!$A$1:$A$49,0),MATCH(orders!J$1,products!$A$1:$G$1,0)) -> M | K1001: =INDEX(products!$A$1:$G$49,MATCH(orders!$D1001,products!$A$1:$A$49,0),MATCH(orders!K$1,products!$A$1:$G$1,0)) -> 0.2 | L1001: =INDEX(products!$A$1:$G$49,MATCH(orders!$D1001,products!$A$1:$A$49,0),MATCH(orders!L$1,products!$A$1:$G$1,0)) -> 4.125 | M1001: =L1001*E1001 -> 12.375 | N1001: =IF(I1001="Rob","Robusta",IF(I1001="Exc","Excelsa",IF(I1001="Ara","Arabica",IF(I1001="Lib","Liberica","")))) -> Excelsa | O1001: =IF(J1001="M","Medium",IF(J1001="L","Light",IF(J1001="D","Dark",""))) -> Medium | P1001: =_xlfn.XLOOKUP(Orders[[#This Row],[Customer ID]],customers!$A$1:$A$1001,customers!$I$1:$I$1001,,0) -> Yes

Sheet customers
A1: Customer ID | B1: Customer Name | C1: Email | D1: Phone Number | E1: Address Line 1 | F1: City | G1: Country | H1: Postcode | I1: Loyalty Card
A2: 17670-51384-MA | B2: Aloisia Allner | C2: aallner0@lulu.com | D2: +1 (862) 817-0124 | E2: 57999 Pepper Wood Alley | F2: Paterson | G2: United States | H2: 7505 | I2: Yes
A3: 73342-18763-UW | B3: Piotr Bote | C3: pbote1@yelp.com | D3: +353 (913) 396-4653 | E3: 2112 Ridgeway Hill | F3: Crumlin | G3: Ireland | H3: D6W | I3: No
A4: 21125-22134-PX | B4: Jami Redholes | C4: jredholes2@tmall.com | D4: +1 (210) 986-6806 | E4: 5214 Bartillon Park | F4: San Antonio | G4: United States | H4: 78205 | I4: Yes
A5: 71253-00052-RN | B5: Dene Azema | C5: dazema3@facebook.com | D5: +1 (217) 418-0714 | E5: 27 Maywood Place | F5: Springfield | G5: United States | H5: 62711 | I5: Yes
A6: 23806-46781-OU | B6: Christoffer O' Shea | D6: +353 (698) 362-9201 | E6: 38980 Manitowish Junction | F6: Cill Airne | G6: Ireland | H6: N41 | I6: No
A7: 86561-91660-RB | B7: Beryle Cottier | D7: +1 (570) 289-7473 | E7: 2651 Stoughton Place | F7: Scranton | G7: United States | H7: 18505 | I7: No
A8: 65223-29612-CB | B8: Shaylynn Lobe | C8: slobe6@nifty.com | D8: +1 (937) 954-4541 | E8: 7005 Mariners Cove Place | F8: Dayton | G8: United States | H8: 45440 | I8: Yes
A9: 21134-81676-FR | B9: Melvin Wharfe | D9: +353 (507) 574-3034 | E9: 7 Straubel Road | F9: Kill | G9: Ireland | H9: P24 | I9: Yes
A10: 03396-68805-ZC | B10: Guthrey Petracci | C10: gpetracci8@livejournal.com | D10: +1 (310) 868-1842 | E10: 949 Paget Parkway | F10: Los Angeles | G10: United States | H10: 90045 | I10: No
A11: 61021-27840-ZN | B11: Rodger Raven | C11: rraven9@ed.gov | D11: +1 (213) 263-0288 | E11: 1 Reinke Avenue | F11: Los Angeles | G11: United States | H11: 90065 | I11: No
A12: 76239-90137-UQ | B12: Ferrell Ferber | C12: fferbera@businesswire.com | D12: +1 (408) 383-5302 | E12: 68 High Crossing Court | F12: San Jose | G12: United States | H12: 95160 | I12: No
A13: 49315-21985-BB | B13: Duky Phizackerly | C13: dphizackerlyb@utexas.edu | D13: +1 (408) 533-6012 | E13: 28643 Bluejay Crossing | F13: San Jose | G13: United States | H13: 95194 | I13: Yes
A14: 34136-36674-OM | B14: Rosaleen Scholar | C14: rscholarc@nyu.edu | D14: +1 (804) 420-0420 | E14: 80915 Montana Park | F14: Richmond | G14: United States | H14: 23285 | I14: No
A15: 39396-12890-PE | B15: Terence Vanyutin | C15: tvanyutind@wix.com | E15: 331 Bunting Hill | F15: Migrate | G15: United States | H15: 41905 | I15: No
A16: 95875-73336-RG | B16: Patrice Trobe | C16: ptrobee@wunderground.com | D16: +1 (314) 240-7896 | E16: 827 Declaration Plaza | F16: Saint Louis | G16: United States | H16: 63131 | I16: Yes
A17: 25473-43727-BY | B17: Llywellyn Oscroft | C17: loscroftf@ebay.co.uk | E17: 022 Roth Place | F17: Philadelphia | G17: United States | H17: 19172 | I17: No
A18: 99643-51048-IQ | B18: Minni Alabaster | C18: malabasterg@hexun.com | D18: +1 (971) 483-6255 | E18: 3 Charing Cross Trail | F18: Portland | G18: United States | H18: 97271 | I18: No
A19: 62173-15287-CU | B19: Rhianon Broxup | C19: rbroxuph@jimdo.com | D19: +1 (713) 663-1338 | E19: 83517 Thierer Court | F19: Houston | G19: United States | H19: 77240 | I19: No
A20: 57611-05522-ST | B20: Pall Redford | C20: predfordi@ow.ly | E20: 7337 Hayes Junction | F20: Caherconlish | G20: Ireland | H20: F45 | I20: Yes
A21: 76664-37050-DT | B21: Aurea Corradino | C21: acorradinoj@harvard.edu | D21: +1 (646) 202-5965 | E21: 698 Canary Terrace | F21: New York City | G21: United States | H21: 10060 | I21: Yes
A22: 84565-53984-SX | B22: Kendal Scardefield | D22: +353 (733) 405-3302 | E22: 3 Northridge Crossing | F22: Clondalkin | G22: Ireland | H22: D24 | I22: Yes
A23: 03090-88267-BQ | B23: Avrit Davidowsky | C23: adavidowskyl@netvibes.com | D23: +1 (616) 481-9962 | E23: 9 Warrior Junction | F23: Grand Rapids | G23: United States | H23: 49560 | I23: No
A24: 37651-47492-NC | B24: Annabel Antuk | C24: aantukm@kickstarter.com | D24: +1 (941) 740-6268 | E24: 77965 Lawn Park | F24: Punta Gorda | G24: United States | H24: 33982 | I24: Yes
A25: 95399-57205-HI | B25: Iorgo Kleinert | C25: ikleinertn@timesonline.co.uk | D25: +1 (360) 352-6598 | E25: 1 Morningstar Lane | F25: Vancouver | G25: United States | H25: 98682 | I25: Yes
A26: 24010-66714-HW | B26: Chrisy Blofeld | C26: cblofeldo@amazon.co.uk | D26: +1 (303) 936-3357 | E26: 013 Talisman Terrace | F26: Englewood | G26: United States | H26: 80150 | I26: No
A27: 07591-92789-UA | B27: Culley Farris | D27: +1 (941) 267-4822 | E27: 4 Mitchell Drive | F27: Punta Gorda | G27: United States | H27: 33982 | I27: Yes
A28: 49231-44455-IC | B28: Selene Shales | C28: sshalesq@umich.edu | D28: +1 (707) 881-5004 | E28: 74 Bultman Plaza | F28: Petaluma | G28: United States | H28: 94975 | I28: Yes
A29: 50124-88608-EO | B29: Vivie Danneil | C29: vdanneilr@mtv.com | D29: +353 (751) 346-0399 | E29: 5626 Darwin Avenue | F29: Tralee | G29: Ireland | H29: V92 | I29: No
A30: 00888-74814-UZ | B30: Theresita Newbury | C30: tnewburys@usda.gov | D30: +353 (803) 587-0026 | E30: 79526 Bultman Lane | F30: Clonskeagh | G30: Ireland | H30: D04 | I30: No
A31: 14158-30713-OB | B31: Mozelle Calcutt | C31: mcalcuttt@baidu.com | D31: +353 (928) 869-1762 | E31: 4389 Russell Way | F31: Rathwire | G31: Ireland | H31: Y25 | I31: Yes
A32: 51427-89175-QJ | B32: Adrian Swaine | D32: +1 (303) 486-9517 | E32: 95 Straubel Hill | F32: Aurora | G32: United States | H32: 80044 | I32: No
A33: 52082-49024-ON | B33: Ray Leivesley | C33: rleivesleyv@canalblog.com | D33: +1 (212) 535-7791 | E33: 91 Stephen Drive | F33: Jamaica | G33: United States | H33: 11407 | I33: No
A34: 04540-43685-DV | B34: Nelly Basezzi | C34: nbasezziw@webeden.co.uk | D34: +353 (125) 815-7345 | E34: 923 Mallard Junction | F34: Bailieborough | G34: Ireland | H34: C15 | I34: Yes
A35: 39123-12846-YJ | B35: Gallard Gatheral | C35: ggatheralx@123-reg.co.uk | E35: 40 Clemons Place | F35: Grand Forks | G35: United States | H35: 58207 | I35: No
A36: 44981-99666-XB | B36: Una Welberry | C36: uwelberryy@ebay.co.uk | D36: +44 (392) 503-8132 | E36: 40915 Schlimgen Park | F36: Upton | G36: United Kingdom | H36: DN21 | I36: Yes
A37: 24825-51803-CQ | B37: Faber Eilhart | C37: feilhartz@who.int | D37: +1 (304) 510-6095 | E37: 6966 Victoria Street | F37: Charleston | G37: United States | H37: 25362 | I37: No
A38: 77634-13918-GJ | B38: Zorina Ponting | C38: zponting10@altervista.org | D38: +1 (501) 172-1476 | E38: 7118 Holmberg Court | F38: Little Rock | G38: United States | H38: 72204 | I38: No
A39: 13694-25001-LX | B39: Silvio Strase | C39: sstrase11@booking.com | D39: +1 (303) 579-8015 | E39: 5 Forest Lane | F39: Denver | G39: United States | H39: 80291 | I39: No
A40: 08523-01791-TI | B40: Dorie de la Tremoille | C40: dde12@unesco.org | D40: +1 (612) 492-5160 | E40: 0817 Dennis Street | F40: Minneapolis | G40: United States | H40: 55458 | I40: No
A41: 49860-68865-AB | B41: Hy Zanetto | E41: 469 Paget Place | F41: Tucson | G41: United States | H41: 85715 | I41: Yes
A42: 21240-83132-SP | B42: Jessica McNess | D42: +1 (504) 545-1478 | E42: 664 Erie Place | F42: New Orleans | G42: United States | H42: 70116 | I42: No
A43: 08350-81623-TF | B43: Lorenzo Yeoland | C43: lyeoland15@pbs.org | D43: +1 (860) 576-2887 | E43: 8510 Merrick Road | F43: Hartford | G43: United States | H43: 6183 | I43: Yes
A44: 73284-01385-SJ | B44: Abigail Tolworthy | C44: atolworthy16@toplist.cz | D44: +1 (801) 722-4425 | E44: 74 Shopko Way | F44: Ogden | G44: United States | H44: 84409 | I44: Yes
A45: 04152-34436-IE | B45: Maurie Bartol | D45: +1 (617) 493-7594 | E45: 7625 Starling Court | F45: Boston | G45: United States | H45: 2216 | I45: No
A46: 06631-86965-XP | B46: Olag Baudassi | C46: obaudassi18@seesaa.net | D46: +1 (585) 356-6251 | E46: 55 Dottie Court | F46: Rochester | G46: United States | H46: 14604 | I46: Yes
A47: 54619-08558-ZU | B47: Petey Kingsbury | C47: pkingsbury19@comcast.net | D47: +1 (917) 705-8224 | E47: 28 Loftsgordon Place | F47: Bronx | G47: United States | H47: 10469 | I47: No
A48: 85589-17020-CX | B48: Donna Baskeyfied | D48: +1 (205) 923-1460 | E48: 7586 Logan Avenue | F48: Birmingham | G48: United States | H48: 35205 | I48: Yes
A49: 36078-91009-WU | B49: Arda Curley | C49: acurley1b@hao123.com | D49: +1 (760) 840-3808 | E49: 45098 Scott Drive | F49: San Bernardino | G49: United States | H49: 92415 | I49: Yes
A50: 15770-27099-GX | B50: Raynor McGilvary | C50: rmcgilvary1c@tamu.edu | E50: 496 Rockefeller Court | F50: Norfolk | G50: United States | H50: 23514 | I50: No
A51: 91460-04823-BX | B51: Isis Pikett | C51: ipikett1d@xinhuanet.com | D51: +1 (202) 871-9039 | E51: 5892 Hauk Drive | F51: Washington | G51: United States | H51: 20409 | I51: No
A52: 45089-52817-WN | B52: Inger Bouldon | C52: ibouldon1e@gizmodo.com | D52: +1 (754) 391-4736 | E52: 925 Barby Circle | F52: Fort Lauderdale | G52: United States | H52: 33355 | I52: No
A53: 76447-50326-IC | B53: Karry Flanders | C53: kflanders1f@over-blog.com | D53: +353 (467) 720-7274 | E53: 88 Blue Bill Park Avenue | F53: Crumlin | G53: Ireland | H53: D6W | I53: Yes
A54: 26333-67911-OL | B54: Hartley Mattioli | C54: hmattioli1g@webmd.com | E54: 126 Valley Edge Street | F54: Kinloch | G54: United Kingdom | H54: PH43 | I54: No
A55: 40768-49176-BL | B55: Horatio Rubberts | C55: hrubberts1h@google.com.hk | D55: +1 (801) 635-8791 | E55: 459 Russell Center | F55: Provo | G55: United States | H55: 84605 | I55: No
A56: 22107-86640-SB | B56: Archambault Gillard | C56: agillard1i@issuu.com | D56: +1 (419) 663-2236 | E56: 97490 Susan Avenue | F56: Toledo | G56: United States | H56: 43666 | I56: No
A57: 09960-34242-LZ | B57: Salomo Cushworth | D57: +1 (609) 409-7044 | E57: 44 Oneill Parkway | F57: Trenton | G57: United States | H57: 8650 | I57: No
A58: 04671-85591-RT | B58: Theda Grizard | C58: tgrizard1k@odnoklassniki.ru | D58: +1 (813) 243-2150 | E58: 6 Knutson Pass | F58: Tampa | G58: United States | H58: 33686 | I58: Yes
A59: 25729-68859-UA | B59: Rozele Relton | C59: rrelton1l@stanford.edu | D59: +1 (850) 626-1181 | E59: 2484 Reindahl Court | F59: Pensacola | G59: United States | H59: 32590 | I59: No
A60: 05501-86351-NX | B60: Willa Rolling | D60: +1 (813) 759-3534 | E60: 3 Mockingbird Plaza | F60: Zephyrhills | G60: United States | H60: 33543 | I60: Yes
A61: 04521-04300-OK | B61: Stanislaus Gilroy | C61: sgilroy1n@eepurl.com | E61: 9120 Harbort Terrace | F61: Saint Paul | G61: United States | H61: 55123 | I61: Yes
A62: 58689-55264-VK | B62: Correy Cottingham | C62: ccottingham1o@wikipedia.org | D62: +1 (260) 764-1820 | E62: 394 Logan Road | F62: Fort Wayne | G62: United States | H62: 46862 | I62: No
A63: 79436-73011-MM | B63: Pammi Endacott | D63: +44 (177) 260-5076 | E63: 5841 Atwood Lane | F63: Wootton | G63: United Kingdom | H63: NN4 | I63: Yes
A64: 65552-60476-KY | B64: Nona Linklater | D64: +1 (239) 347-9766 | E64: 856 Bonner Parkway | F64: Naples | G64: United States | H64: 34114 | I64: Yes
A65: 69904-02729-YS | B65: Annadiane Dykes | C65: adykes1r@eventbrite.com | D65: +1 (312) 111-6203 | E65: 31 Northport Terrace | F65: Chicago | G65: United States | H65: 60681 | I65: No
A66: 01433-04270-AX | B66: Felecia Dodgson | D66: +1 (973) 434-8662 | E66: 48053 8th Crossing | F66: Newark | G66: United States | H66: 7104 | I66: Yes
A67: 14204-14186-LA | B67: Angelia Cockrem | C67: acockrem1t@engadget.com | D67: +1 (571) 316-8217 | E67: 1 Sherman Alley | F67: Vienna | G67: United States | H67: 22184 | I67: Yes
A68: 32948-34398-HC | B68: Belvia Umpleby | C68: bumpleby1u@soundcloud.com | D68: +1 (682) 627-0888 | E68: 710 Prairie Rose Terrace | F68: Fort Worth | G68: United States | H68: 76178 | I68: Yes
A69: 77343-52608-FF | B69: Nat Saleway | C69: nsaleway1v@dedecms.com | D69: +1 (323) 473-0294 | E69: 0780 Anthes Plaza | F69: Burbank | G69: United States | H69: 91505 | I69: No
A70: 42770-36274-QA | B70: Hayward Goulter | C70: hgoulter1w@abc.net.au | D70: +1 (423) 764-7751 | E70: 2081 Mariners Cove Drive | F70: Kingsport | G70: United States | H70: 37665 | I70: No
A71: 14103-58987-ZU | B71: Gay Rizzello | C71: grizzello1x@symantec.com | D71: +44 (247) 225-8003 | E71: 21 Schmedeman Crossing | F71: Liverpool | G71: United Kingdom | H71: L33 | I71: Yes
A72: 69958-32065-SW | B72: Shannon List | C72: slist1y@mapquest.com | D72: +1 (614) 279-9816 | E72: 7123 Algoma Center | F72: Columbus | G72: United States | H72: 43231 | I72: No
A73: 69533-84907-FA | B73: Shirlene Edmondson | C73: sedmondson1z@theguardian.com | D73: +353 (248) 428-7978 | E73: 4752 International Point | F73: Newmarket on Fergus | G73: Ireland | H73: P17 | I73: No
A74: 76005-95461-CI | B74: Aurlie McCarl | D74: +1 (504) 209-2724 | E74: 731 David Park | F74: New Orleans | G74: United States | H74: 70183 | I74: No
A75: 15395-90855-VB | B75: Alikee Carryer | D75: +1 (704) 799-5219 | E75: 247 Helena Drive | F75: Charlotte | G75: United States | H75: 28230 | I75: Yes
A76: 80640-45811-LB | B76: Jennifer Rangall | C76: jrangall22@newsvine.com | D76: +1 (781) 512-6637 | E76: 0 Grasskamp Lane | F76: Springfield | G76: United States | H76: 1114 | I76: Yes
A77: 28476-04082-GR | B77: Kipper Boorn | C77: kboorn23@ezinearticles.com | D77: +353 (359) 134-1550 | E77: 9513 Meadow Ridge Parkway | F77: Listowel | G77: Ireland | H77: V31 | I77: Yes
A78: 12018-75670-EU | B78: Melania Beadle | D78: +353 (569) 458-9673 | E78: 4418 Quincy Terrace | F78: Moycullen | G78: Ireland | H78: A41 | I78: Yes
A79: 86437-17399-FK | B79: Colene Elgey | C79: celgey25@webs.com | D79: +1 (432) 261-0702 | E79: 45 Marcy Crossing | F79: Midland | G79: United States | H79: 79705 | I79: No
A80: 62979-53167-ML | B80: Lothaire Mizzi | C80: lmizzi26@rakuten.co.jp | D80: +1 (214) 719-8530 | E80: 74 Atwood Lane | F80: Dallas | G80: United States | H80: 75323 | I80: Yes
A81: 54810-81899-HL | B81: Cletis Giacomazzo | C81: cgiacomazzo27@jigsy.com | D81: +1 (571) 703-2064 | E81: 817 Ridgeway Hill | F81: Dulles | G81: United States | H81: 20189 | I81: No
A82: 26103-41504-IB | B82: Ami Arnow | C82: aarnow28@arizona.edu | D82: +1 (650) 238-1964 | E82: 12 Oakridge Court | F82: Oakland | G82: United States | H82: 94627 | I82: Yes
A83: 76534-45229-SG | B83: Sheppard Yann | C83: syann29@senate.gov | D83: +1 (719) 803-5276 | E83: 4 Farmco Place | F83: Colorado Springs | G83: United States | H83: 80930 | I83: Yes
A84: 81744-27332-RR | B84: Bunny Naulls | C84: bnaulls2a@tiny.cc | D84: +353 (809) 128-0755 | E84: 595 Melby Avenue | F84: Adare | G84: Ireland | H84: H54 | I84: Yes
A85: 91513-75657-PH | B85: Hally Lorait | D85: +1 (716) 869-3749 | E85: 80 Jana Avenue | F85: Buffalo | G85: United States | H85: 14205 | I85: Yes
A86: 30373-66619-CB | B86: Zaccaria Sherewood | C86: zsherewood2c@apache.org | D86: +1 (209) 433-7924 | E86: 1325 Jay Terrace | F86: Fresno | G86: United States | H86: 93715 | I86: No
A87: 31582-23562-FM | B87: Jeffrey Dufaire | C87: jdufaire2d@fc2.com | E87: 8 Buell Junction | F87: Fort Worth | G87: United States | H87: 76121 | I87: No
A88: 58638-01029-CB | B88: Blancha McAmish | C88: bmcamish2e@tripadvisor.com | E88: 5484 Stephen Court | F88: Oklahoma City | G88: United States | H88: 73179 | I88: Yes
A89: 81431-12577-VD | B89: Beitris Keaveney | C89: bkeaveney2f@netlog.com | E89: 67319 Redwing Parkway | F89: Beaumont | G89: United States | H89: 77705 | I89: No
A90: 68894-91205-MP | B90: Elna Grise | C90: egrise2g@cargocollective.com | E90: 92 Becker Circle | F90: Reno | G90: United States | H90: 89519 | I90: No
A91: 87602-55754-VN | B91: Torie Gottelier | C91: tgottelier2h@vistaprint.com | D91: +1 (816) 743-8492 | E91: 426 Division Avenue | F91: Kansas City | G91: United States | H91: 64136 | I91: No
A92: 39181-35745-WH | B92: Loydie Langlais | D92: +353 (576) 222-5069 | E92: 290 Ilene Street | F92: Crumlin | G92: Ireland | H92: D6W | I92: Yes
A93: 30381-64762-NG | B93: Adham Greenhead | C93: agreenhead2j@dailymail.co.uk | D93: +1 (951) 797-0738 | E93: 0062 Spenser Place | F93: Corona | G93: United States | H93: 92878 | I93: No
A94: 17503-27693-ZH | B94: Hamish MacSherry | D94: +1 (512) 430-4374 | E94: 7 Brentwood Plaza | F94: Austin | G94: United States | H94: 78759 | I94: Yes
A95: 89442-35633-HJ | B95: Else Langcaster | C95: elangcaster2l@spotify.com | D95: +44 (547) 590-3103 | E95: 3658 Jenna Street | F95: Normanton | G95: United Kingdom | H95: LE15 | I95: Yes
A96: 13654-85265-IL | B96: Rudy Farquharson | E96: 30178 Claremont Road | F96: Charlesland | G96: Ireland | H96: A63 | I96: Yes
A97: 40946-22090-FP | B97: Norene Magauran | C97: nmagauran2n@51.la | E97: 567 Artisan Place | F97: Fresno | G97: United States | H97: 93762 | I97: No
A98: 29050-93691-TS | B98: Vicki Kirdsch | C98: vkirdsch2o@google.fr | E98: 0263 Golf Street | F98: Saint Louis | G98: United States | H98: 63150 | I98: No
A99: 64395-74865-WF | B99: Ilysa Whapple | C99: iwhapple2p@com.com | D99: +1 (559) 522-1152 | E99: 41598 Everett Drive | F99: Fresno | G99: United States | H99: 93726 | I99: No
A100: 81861-66046-SU | B100: Ruy Cancellieri | D100: +353 (338) 743-8327 | E100: 251 Welch Parkway | F100: Confey | G100: Ireland | H100: A86 | I100: No
...

Sheet products
A1: Product ID | B1: Coffee Type | C1: Roast Type | D1: Size | E1: Unit Price | F1: Price per 100g | G1: Profit
A2: A-L-0.2 | B2: Ara | C2: L | D2: 0.2 | E2: 3.885 | F2: 1.9425 | G2: 0.34965
A3: A-L-0.5 | B3: Ara | C3: L | D3: 0.5 | E3: 7.77 | F3: 1.554 | G3: 0.6993
A4: A-L-1 | B4: Ara | C4: L | D4: 1 | E4: 12.95 | F4: 1.295 | G4: 1.1655
A5: A-L-2.5 | B5: Ara | C5: L | D5: 2.5 | E5: 29.785 | F5: 1.1914 | G5: 2.68065
A6: A-M-0.2 | B6: Ara | C6: M | D6: 0.2 | E6: 3.375 | F6: 1.6875 | G6: 0.30375
A7: A-M-0.5 | B7: Ara | C7: M | D7: 0.5 | E7: 6.75 | F7: 1.35 | G7: 0.6075
A8: A-M-1 | B8: Ara | C8: M | D8: 1 | E8: 11.25 | F8: 1.125 | G8: 1.0125
A9: A-M-2.5 | B9: Ara | C9: M | D9: 2.5 | E9: 25.875 | F9: 1.035 | G9: 2.32875
A10: A-D-0.2 | B10: Ara | C10: D | D10: 0.2 | E10: 2.985 | F10: 1.4925 | G10: 0.26865
A11: A-D-0.5 | B11: Ara | C11: D | D11: 0.5 | E11: 5.97 | F11: 1.194 | G11: 0.5373
A12: A-D-1 | B12: Ara | C12: D | D12: 1 | E12: 9.95 | F12: 0.995 | G12: 0.8955
A13: A-D-2.5 | B13: Ara | C13: D | D13: 2.5 | E13: 22.885 | F13: 0.9154 | G13: 2.05965
... A49: E-D-2.5 | B49: Exc | C49: D | D49: 2.5 | E49: 27.945 | F49: 1.1178 | G49: 3.07395
